{"book":"Ps","chapter":139,"verses":[{"id":"Ps.139.1","bookId":"Ps","chapter":139,"verse":1,"reference":"Psalms 139:1","text":"εἰς τὸ τέλος ψαλμὸς τῷ Δαυιδ","words":[{"position":1,"surface":"εἰς","lemma":"εἰς","strongs":"1519","morph":{"partOfSpeech":"Preposition","casus":null,"number":null,"gender":null,"tense":null,"voice":null,"mood":null,"person":null},"id":"Ps.139.1.1","verseId":"Ps.139.1"},{"position":2,"surface":"τὸ","lemma":"τὸ","strongs":"3588","morph":{"partOfSpeech":"Article","casus":"Accusative","number":"Singular","gender":"Neuter","tense":null,"voice":null,"mood":null,"person":null},"id":"Ps.139.1.2","verseId":"Ps.139.1"},{"position":3,"surface":"τέλος","lemma":"τέλος","strongs":"5056","morph":{"partOfSpeech":"Noun","casus":"Accusative","number":"Singular","gender":"Neuter","tense":null,"voice":null,"mood":null,"person":null},"id":"Ps.139.1.3","verseId":"Ps.139.1"},{"position":4,"surface":"ψαλμὸς","lemma":"ψαλμὸς","strongs":"5568","morph":{"partOfSpeech":"Noun","casus":"Nominative","number":"Singular","gender":"Masculine","tense":null,"voice":null,"mood":null,"person":null},"id":"Ps.139.1.4","verseId":"Ps.139.1"},{"position":5,"surface":"τῷ","lemma":"τῷ","strongs":"3588","morph":{"partOfSpeech":"Article","casus":"Dative","number":"Singular","gender":"Masculine","tense":null,"voice":null,"mood":null,"person":null},"id":"Ps.139.1.5","verseId":"Ps.139.1"},{"position":6,"surface":"Δαυιδ","lemma":"Δαυιδ","strongs":"1138","morph":{"partOfSpeech":"Noun","casus":"Dative","number":"Singular","gender":"Masculine","tense":null,"voice":null,"mood":null,"person":null},"id":"Ps.139.1.6","verseId":"Ps.139.1"}]},{"id":"Ps.139.2","bookId":"Ps","chapter":139,"verse":2,"reference":"Psalms 139:2","text":"ἐξελοῦ με κύριε ἐξ ἀνθρώπου πονηροῦ ἀπὸ ἀνδρὸς ἀδίκου ῥῦσαί με","words":[{"position":1,"surface":"ἐξελοῦ","lemma":"ἐξελοῦ","strongs":"1807","morph":{"partOfSpeech":"Verb","casus":null,"number":"Singular","gender":null,"tense":"Aorist","voice":"Active","mood":"Imperative","person":"2"},"id":"Ps.139.2.1","verseId":"Ps.139.2"},{"position":2,"surface":"με","lemma":"με","strongs":"3165","morph":{"partOfSpeech":"RP","casus":"Accusative","number":"Singular","tense":null,"voice":null,"mood":null,"person":null},"id":"Ps.139.2.2","verseId":"Ps.139.2"},{"position":3,"surface":"κύριε","lemma":"κύριε","strongs":"2962","morph":{"partOfSpeech":"Noun","casus":"Vocative","number":"Singular","gender":"Masculine","tense":null,"voice":null,"mood":null,"person":null},"id":"Ps.139.2.3","verseId":"Ps.139.2"},{"position":4,"surface":"ἐξ","lemma":"ἐξ","strongs":"1537","morph":{"partOfSpeech":"Preposition","casus":null,"number":null,"gender":null,"tense":null,"voice":null,"mood":null,"person":null},"id":"Ps.139.2.4","verseId":"Ps.139.2"},{"position":5,"surface":"ἀνθρώπου","lemma":"ἀνθρώπου","strongs":"444","morph":{"partOfSpeech":"Noun","casus":"Genitive","number":"Singular","gender":"Masculine","tense":null,"voice":null,"mood":null,"person":null},"id":"Ps.139.2.5","verseId":"Ps.139.2"},{"position":6,"surface":"πονηροῦ","lemma":"πονηροῦ","strongs":"4190","morph":{"partOfSpeech":"Adjective","casus":"Genitive","number":"Singular","gender":"Masculine","tense":null,"voice":null,"mood":null,"person":null},"id":"Ps.139.2.6","verseId":"Ps.139.2"},{"position":7,"surface":"ἀπὸ","lemma":"ἀπὸ","strongs":"575","morph":{"partOfSpeech":"Preposition","casus":null,"number":null,"gender":null,"tense":null,"voice":null,"mood":null,"person":null},"id":"Ps.139.2.7","verseId":"Ps.139.2"},{"position":8,"surface":"ἀνδρὸς","lemma":"ἀνδρὸς","strongs":"435","morph":{"partOfSpeech":"Noun","casus":"Genitive","number":"Singular","gender":"Masculine","tense":null,"voice":null,"mood":null,"person":null},"id":"Ps.139.2.8","verseId":"Ps.139.2"},{"position":9,"surface":"ἀδίκου","lemma":"ἀδίκου","strongs":"94","morph":{"partOfSpeech":"Adjective","casus":"Genitive","number":"Singular","gender":"Masculine","tense":null,"voice":null,"mood":null,"person":null},"id":"Ps.139.2.9","verseId":"Ps.139.2"},{"position":10,"surface":"ῥῦσαί","lemma":"ῥῦσαί","strongs":"4506","morph":{"partOfSpeech":"Verb","casus":null,"number":"Singular","gender":null,"tense":"Aorist","voice":"Active","mood":"Imperative","person":"2"},"id":"Ps.139.2.10","verseId":"Ps.139.2"},{"position":11,"surface":"με","lemma":"με","strongs":"3165","morph":{"partOfSpeech":"RP","casus":"Accusative","number":"Singular","tense":null,"voice":null,"mood":null,"person":null},"id":"Ps.139.2.11","verseId":"Ps.139.2"}]},{"id":"Ps.139.3","bookId":"Ps","chapter":139,"verse":3,"reference":"Psalms 139:3","text":"οἵτινες ἐλογίσαντο ἀδικίας ἐν καρδίᾳ ὅλην τὴν ἡμέραν παρετάσσοντο πολέμους","words":[{"position":1,"surface":"οἵτινες","lemma":"οἵτινες","strongs":"3748","morph":{"partOfSpeech":"Indefinite Pronoun","casus":"Nominative","number":"Plural","gender":"Masculine","tense":null,"voice":null,"mood":null,"person":null},"id":"Ps.139.3.1","verseId":"Ps.139.3"},{"position":2,"surface":"ἐλογίσαντο","lemma":"ἐλογίσαντο","strongs":"3049","morph":{"partOfSpeech":"Verb","casus":null,"number":"Plural","gender":null,"tense":"Aorist","voice":"Middle","mood":"Indicative","person":"3"},"id":"Ps.139.3.2","verseId":"Ps.139.3"},{"position":3,"surface":"ἀδικίας","lemma":"ἀδικίας","strongs":"93","morph":{"partOfSpeech":"Noun","casus":"Accusative","number":"Plural","gender":"Feminine","tense":null,"voice":null,"mood":null,"person":null},"id":"Ps.139.3.3","verseId":"Ps.139.3"},{"position":4,"surface":"ἐν","lemma":"ἐν","strongs":"1722","morph":{"partOfSpeech":"Preposition","casus":null,"number":null,"gender":null,"tense":null,"voice":null,"mood":null,"person":null},"id":"Ps.139.3.4","verseId":"Ps.139.3"},{"position":5,"surface":"καρδίᾳ","lemma":"καρδίᾳ","strongs":"2588","morph":{"partOfSpeech":"Noun","casus":"Dative","number":"Singular","gender":"Feminine","tense":null,"voice":null,"mood":null,"person":null},"id":"Ps.139.3.5","verseId":"Ps.139.3"},{"position":6,"surface":"ὅλην","lemma":"ὅλην","strongs":"3650","morph":{"partOfSpeech":"Adjective","casus":"Accusative","number":"Singular","gender":"Feminine","tense":null,"voice":null,"mood":null,"person":null},"id":"Ps.139.3.6","verseId":"Ps.139.3"},{"position":7,"surface":"τὴν","lemma":"τὴν","strongs":"3588","morph":{"partOfSpeech":"Article","casus":"Accusative","number":"Singular","gender":"Feminine","tense":null,"voice":null,"mood":null,"person":null},"id":"Ps.139.3.7","verseId":"Ps.139.3"},{"position":8,"surface":"ἡμέραν","lemma":"ἡμέραν","strongs":"2250","morph":{"partOfSpeech":"Noun","casus":"Accusative","number":"Singular","gender":"Feminine","tense":null,"voice":null,"mood":null,"person":null},"id":"Ps.139.3.8","verseId":"Ps.139.3"},{"position":9,"surface":"παρετάσσοντο","lemma":"παρετάσσοντο","strongs":"","morph":{"partOfSpeech":"Verb","casus":null,"number":"Plural","gender":null,"tense":"Imperfect","voice":"Middle","mood":"Indicative","person":"3"},"id":"Ps.139.3.9","verseId":"Ps.139.3"},{"position":10,"surface":"πολέμους","lemma":"πολέμους","strongs":"4171","morph":{"partOfSpeech":"Noun","casus":"Accusative","number":"Plural","gender":"Masculine","tense":null,"voice":null,"mood":null,"person":null},"id":"Ps.139.3.10","verseId":"Ps.139.3"}]},{"id":"Ps.139.4","bookId":"Ps","chapter":139,"verse":4,"reference":"Psalms 139:4","text":"ἠκόνησαν γλῶσσαν αὐτῶν ὡσεὶ ὄφεως ἰὸς ἀσπίδων ὑπὸ τὰ χείλη αὐτῶν διάψαλμα","words":[{"position":1,"surface":"ἠκόνησαν","lemma":"ἠκόνησαν","strongs":"","morph":{"partOfSpeech":"Verb","casus":null,"number":"Plural","gender":null,"tense":"Aorist","voice":"Active","mood":"Indicative","person":"3"},"id":"Ps.139.4.1","verseId":"Ps.139.4"},{"position":2,"surface":"γλῶσσαν","lemma":"γλῶσσαν","strongs":"1100","morph":{"partOfSpeech":"Noun","casus":"Accusative","number":"Singular","gender":"Feminine","tense":null,"voice":null,"mood":null,"person":null},"id":"Ps.139.4.2","verseId":"Ps.139.4"},{"position":3,"surface":"αὐτῶν","lemma":"αὐτῶν","strongs":"846","morph":{"partOfSpeech":"RP","casus":"Genitive","number":"Plural","gender":"Masculine","tense":null,"voice":null,"mood":null,"person":null},"id":"Ps.139.4.3","verseId":"Ps.139.4"},{"position":4,"surface":"ὡσεὶ","lemma":"ὡσεὶ","strongs":"5616","morph":{"partOfSpeech":"Adverb","casus":null,"number":null,"gender":null,"tense":null,"voice":null,"mood":null,"person":null},"id":"Ps.139.4.4","verseId":"Ps.139.4"},{"position":5,"surface":"ὄφεως","lemma":"ὄφεως","strongs":"3789","morph":{"partOfSpeech":"Noun","casus":"Genitive","number":"Singular","gender":"Masculine","tense":null,"voice":null,"mood":null,"person":null},"id":"Ps.139.4.5","verseId":"Ps.139.4"},{"position":6,"surface":"ἰὸς","lemma":"ἰὸς","strongs":"2447","morph":{"partOfSpeech":"Noun","casus":"Nominative","number":"Singular","gender":"Masculine","tense":null,"voice":null,"mood":null,"person":null},"id":"Ps.139.4.6","verseId":"Ps.139.4"},{"position":7,"surface":"ἀσπίδων","lemma":"ἀσπίδων","strongs":"785","morph":{"partOfSpeech":"Noun","casus":"Genitive","number":"Plural","gender":"Feminine","tense":null,"voice":null,"mood":null,"person":null},"id":"Ps.139.4.7","verseId":"Ps.139.4"},{"position":8,"surface":"ὑπὸ","lemma":"ὑπὸ","strongs":"5259","morph":{"partOfSpeech":"Preposition","casus":null,"number":null,"gender":null,"tense":null,"voice":null,"mood":null,"person":null},"id":"Ps.139.4.8","verseId":"Ps.139.4"},{"position":9,"surface":"τὰ","lemma":"τὰ","strongs":"3588","morph":{"partOfSpeech":"Article","casus":"Accusative","number":"Plural","gender":"Neuter","tense":null,"voice":null,"mood":null,"person":null},"id":"Ps.139.4.9","verseId":"Ps.139.4"},{"position":10,"surface":"χείλη","lemma":"χείλη","strongs":"5491","morph":{"partOfSpeech":"Noun","casus":"Accusative","number":"Plural","gender":"Neuter","tense":null,"voice":null,"mood":null,"person":null},"id":"Ps.139.4.10","verseId":"Ps.139.4"},{"position":11,"surface":"αὐτῶν","lemma":"αὐτῶν","strongs":"846","morph":{"partOfSpeech":"RP","casus":"Genitive","number":"Plural","gender":"Masculine","tense":null,"voice":null,"mood":null,"person":null},"id":"Ps.139.4.11","verseId":"Ps.139.4"},{"position":12,"surface":"διάψαλμα","lemma":"διάψαλμα","strongs":"","morph":{"partOfSpeech":"Noun","casus":"Nominative","number":"Singular","gender":"Neuter","tense":null,"voice":null,"mood":null,"person":null},"id":"Ps.139.4.12","verseId":"Ps.139.4"}]},{"id":"Ps.139.5","bookId":"Ps","chapter":139,"verse":5,"reference":"Psalms 139:5","text":"φύλαξόν με κύριε ἐκ χειρὸς ἁμαρτωλοῦ ἀπὸ ἀνθρώπων ἀδίκων ἐξελοῦ με οἵτινες ἐλογίσαντο ὑποσκελίσαι τὰ διαβήματά μου","words":[{"position":1,"surface":"φύλαξόν","lemma":"φύλαξόν","strongs":"5442","morph":{"partOfSpeech":"Verb","casus":null,"number":"Singular","gender":null,"tense":"Aorist","voice":"Active","mood":"Imperative","person":"2"},"id":"Ps.139.5.1","verseId":"Ps.139.5"},{"position":2,"surface":"με","lemma":"με","strongs":"3165","morph":{"partOfSpeech":"RP","casus":"Accusative","number":"Singular","tense":null,"voice":null,"mood":null,"person":null},"id":"Ps.139.5.2","verseId":"Ps.139.5"},{"position":3,"surface":"κύριε","lemma":"κύριε","strongs":"2962","morph":{"partOfSpeech":"Noun","casus":"Vocative","number":"Singular","gender":"Masculine","tense":null,"voice":null,"mood":null,"person":null},"id":"Ps.139.5.3","verseId":"Ps.139.5"},{"position":4,"surface":"ἐκ","lemma":"ἐκ","strongs":"1537","morph":{"partOfSpeech":"Preposition","casus":null,"number":null,"gender":null,"tense":null,"voice":null,"mood":null,"person":null},"id":"Ps.139.5.4","verseId":"Ps.139.5"},{"position":5,"surface":"χειρὸς","lemma":"χειρὸς","strongs":"5495","morph":{"partOfSpeech":"Noun","casus":"Genitive","number":"Singular","gender":"Feminine","tense":null,"voice":null,"mood":null,"person":null},"id":"Ps.139.5.5","verseId":"Ps.139.5"},{"position":6,"surface":"ἁμαρτωλοῦ","lemma":"ἁμαρτωλοῦ","strongs":"268","morph":{"partOfSpeech":"Adjective","casus":"Genitive","number":"Singular","gender":"Masculine","tense":null,"voice":null,"mood":null,"person":null},"id":"Ps.139.5.6","verseId":"Ps.139.5"},{"position":7,"surface":"ἀπὸ","lemma":"ἀπὸ","strongs":"575","morph":{"partOfSpeech":"Preposition","casus":null,"number":null,"gender":null,"tense":null,"voice":null,"mood":null,"person":null},"id":"Ps.139.5.7","verseId":"Ps.139.5"},{"position":8,"surface":"ἀνθρώπων","lemma":"ἀνθρώπων","strongs":"444","morph":{"partOfSpeech":"Noun","casus":"Genitive","number":"Plural","gender":"Masculine","tense":null,"voice":null,"mood":null,"person":null},"id":"Ps.139.5.8","verseId":"Ps.139.5"},{"position":9,"surface":"ἀδίκων","lemma":"ἀδίκων","strongs":"94","morph":{"partOfSpeech":"Adjective","casus":"Genitive","number":"Plural","gender":"Masculine","tense":null,"voice":null,"mood":null,"person":null},"id":"Ps.139.5.9","verseId":"Ps.139.5"},{"position":10,"surface":"ἐξελοῦ","lemma":"ἐξελοῦ","strongs":"1807","morph":{"partOfSpeech":"Verb","casus":null,"number":"Singular","gender":null,"tense":"Aorist","voice":"Middle","mood":"Imperative","person":"2"},"id":"Ps.139.5.10","verseId":"Ps.139.5"},{"position":11,"surface":"με","lemma":"με","strongs":"3165","morph":{"partOfSpeech":"RP","casus":"Accusative","number":"Singular","tense":null,"voice":null,"mood":null,"person":null},"id":"Ps.139.5.11","verseId":"Ps.139.5"},{"position":12,"surface":"οἵτινες","lemma":"οἵτινες","strongs":"3748","morph":{"partOfSpeech":"Indefinite Pronoun","casus":"Nominative","number":"Plural","gender":"Masculine","tense":null,"voice":null,"mood":null,"person":null},"id":"Ps.139.5.12","verseId":"Ps.139.5"},{"position":13,"surface":"ἐλογίσαντο","lemma":"ἐλογίσαντο","strongs":"3049","morph":{"partOfSpeech":"Verb","casus":null,"number":"Plural","gender":null,"tense":"Aorist","voice":"Middle","mood":"Indicative","person":"3"},"id":"Ps.139.5.13","verseId":"Ps.139.5"},{"position":14,"surface":"ὑποσκελίσαι","lemma":"ὑποσκελίσαι","strongs":"","morph":{"partOfSpeech":"Verb","casus":null,"number":null,"gender":null,"tense":"Aorist","voice":"Active","mood":"Infinitive","person":null},"id":"Ps.139.5.14","verseId":"Ps.139.5"},{"position":15,"surface":"τὰ","lemma":"τὰ","strongs":"3588","morph":{"partOfSpeech":"Article","casus":"Accusative","number":"Plural","gender":"Neuter","tense":null,"voice":null,"mood":null,"person":null},"id":"Ps.139.5.15","verseId":"Ps.139.5"},{"position":16,"surface":"διαβήματά","lemma":"διαβήματά","strongs":"","morph":{"partOfSpeech":"Noun","casus":"Accusative","number":"Plural","gender":"Neuter","tense":null,"voice":null,"mood":null,"person":null},"id":"Ps.139.5.16","verseId":"Ps.139.5"},{"position":17,"surface":"μου","lemma":"μου","strongs":"3450","morph":{"partOfSpeech":"RP","casus":"Genitive","number":"Singular","tense":null,"voice":null,"mood":null,"person":null},"id":"Ps.139.5.17","verseId":"Ps.139.5"}]},{"id":"Ps.139.6","bookId":"Ps","chapter":139,"verse":6,"reference":"Psalms 139:6","text":"ἔκρυψαν ὑπερήφανοι παγίδα μοι καὶ σχοινία διέτειναν παγίδας τοῖς ποσίν μου ἐχόμενα τρίβου σκάνδαλον ἔθεντό μοι διάψαλμα","words":[{"position":1,"surface":"ἔκρυψαν","lemma":"ἔκρυψαν","strongs":"2928","morph":{"partOfSpeech":"Verb","casus":null,"number":"Plural","gender":null,"tense":"Aorist","voice":"Active","mood":"Indicative","person":"3"},"id":"Ps.139.6.1","verseId":"Ps.139.6"},{"position":2,"surface":"ὑπερήφανοι","lemma":"ὑπερήφανοι","strongs":"5244","morph":{"partOfSpeech":"Adjective","casus":"Nominative","number":"Plural","gender":"Masculine","tense":null,"voice":null,"mood":null,"person":null},"id":"Ps.139.6.2","verseId":"Ps.139.6"},{"position":3,"surface":"παγίδα","lemma":"παγίδα","strongs":"3803","morph":{"partOfSpeech":"Noun","casus":"Accusative","number":"Singular","gender":"Feminine","tense":null,"voice":null,"mood":null,"person":null},"id":"Ps.139.6.3","verseId":"Ps.139.6"},{"position":4,"surface":"μοι","lemma":"μοι","strongs":"3427","morph":{"partOfSpeech":"RP","casus":"Dative","number":"Singular","tense":null,"voice":null,"mood":null,"person":null},"id":"Ps.139.6.4","verseId":"Ps.139.6"},{"position":5,"surface":"καὶ","lemma":"καὶ","strongs":"2532","morph":{"partOfSpeech":"Conjunction","casus":null,"number":null,"gender":null,"tense":null,"voice":null,"mood":null,"person":null},"id":"Ps.139.6.5","verseId":"Ps.139.6"},{"position":6,"surface":"σχοινία","lemma":"σχοινία","strongs":"4979","morph":{"partOfSpeech":"Noun","casus":"Accusative","number":"Plural","gender":"Neuter","tense":null,"voice":null,"mood":null,"person":null},"id":"Ps.139.6.6","verseId":"Ps.139.6"},{"position":7,"surface":"διέτειναν","lemma":"διέτειναν","strongs":"","morph":{"partOfSpeech":"Verb","casus":null,"number":"Plural","gender":null,"tense":"Aorist","voice":"Active","mood":"Indicative","person":"3"},"id":"Ps.139.6.7","verseId":"Ps.139.6"},{"position":8,"surface":"παγίδας","lemma":"παγίδας","strongs":"3803","morph":{"partOfSpeech":"Noun","casus":"Accusative","number":"Plural","gender":"Feminine","tense":null,"voice":null,"mood":null,"person":null},"id":"Ps.139.6.8","verseId":"Ps.139.6"},{"position":9,"surface":"τοῖς","lemma":"τοῖς","strongs":"3588","morph":{"partOfSpeech":"Article","casus":"Dative","number":"Plural","gender":"Masculine","tense":null,"voice":null,"mood":null,"person":null},"id":"Ps.139.6.9","verseId":"Ps.139.6"},{"position":10,"surface":"ποσίν","lemma":"ποσίν","strongs":"4228","morph":{"partOfSpeech":"Noun","casus":"Dative","number":"Plural","gender":"Masculine","tense":null,"voice":null,"mood":null,"person":null},"id":"Ps.139.6.10","verseId":"Ps.139.6"},{"position":11,"surface":"μου","lemma":"μου","strongs":"3450","morph":{"partOfSpeech":"RP","casus":"Genitive","number":"Singular","tense":null,"voice":null,"mood":null,"person":null},"id":"Ps.139.6.11","verseId":"Ps.139.6"},{"position":12,"surface":"ἐχόμενα","lemma":"ἐχόμενα","strongs":"2192","morph":{"partOfSpeech":"Verb","casus":"Accusative","number":"Plural","gender":"Neuter","tense":"Present","voice":"Middle","mood":"Participle","person":null},"id":"Ps.139.6.12","verseId":"Ps.139.6"},{"position":13,"surface":"τρίβου","lemma":"τρίβου","strongs":"5147","morph":{"partOfSpeech":"Noun","casus":"Genitive","number":"Singular","gender":"Feminine","tense":null,"voice":null,"mood":null,"person":null},"id":"Ps.139.6.13","verseId":"Ps.139.6"},{"position":14,"surface":"σκάνδαλον","lemma":"σκάνδαλον","strongs":"4625","morph":{"partOfSpeech":"Noun","casus":"Accusative","number":"Singular","gender":"Neuter","tense":null,"voice":null,"mood":null,"person":null},"id":"Ps.139.6.14","verseId":"Ps.139.6"},{"position":15,"surface":"ἔθεντό","lemma":"ἔθεντό","strongs":"5087","morph":{"partOfSpeech":"Verb","casus":null,"number":"Plural","gender":null,"tense":"Aorist","voice":"Middle","mood":"Indicative","person":"3"},"id":"Ps.139.6.15","verseId":"Ps.139.6"},{"position":16,"surface":"μοι","lemma":"μοι","strongs":"3427","morph":{"partOfSpeech":"RP","casus":"Dative","number":"Singular","tense":null,"voice":null,"mood":null,"person":null},"id":"Ps.139.6.16","verseId":"Ps.139.6"},{"position":17,"surface":"διάψαλμα","lemma":"διάψαλμα","strongs":"","morph":{"partOfSpeech":"Noun","casus":"Nominative","number":"Singular","gender":"Neuter","tense":null,"voice":null,"mood":null,"person":null},"id":"Ps.139.6.17","verseId":"Ps.139.6"}]},{"id":"Ps.139.7","bookId":"Ps","chapter":139,"verse":7,"reference":"Psalms 139:7","text":"εἶπα τῷ κυρίῳ θεός μου εἶ σύ ἐνώτισαι κύριε τὴν φωνὴν τῆς δεήσεώς μου","words":[{"position":1,"surface":"εἶπα","lemma":"εἶπα","strongs":"2036","morph":{"partOfSpeech":"Verb","casus":null,"number":"Singular","gender":null,"tense":"Aorist","voice":"Active","mood":"Indicative","person":"1"},"id":"Ps.139.7.1","verseId":"Ps.139.7"},{"position":2,"surface":"τῷ","lemma":"τῷ","strongs":"3588","morph":{"partOfSpeech":"Article","casus":"Dative","number":"Singular","gender":"Masculine","tense":null,"voice":null,"mood":null,"person":null},"id":"Ps.139.7.2","verseId":"Ps.139.7"},{"position":3,"surface":"κυρίῳ","lemma":"κυρίῳ","strongs":"2962","morph":{"partOfSpeech":"Noun","casus":"Dative","number":"Singular","gender":"Masculine","tense":null,"voice":null,"mood":null,"person":null},"id":"Ps.139.7.3","verseId":"Ps.139.7"},{"position":4,"surface":"θεός","lemma":"θεός","strongs":"2316","morph":{"partOfSpeech":"Noun","casus":"Nominative","number":"Singular","gender":"Masculine","tense":null,"voice":null,"mood":null,"person":null},"id":"Ps.139.7.4","verseId":"Ps.139.7"},{"position":5,"surface":"μου","lemma":"μου","strongs":"3450","morph":{"partOfSpeech":"RP","casus":"Genitive","number":"Singular","tense":null,"voice":null,"mood":null,"person":null},"id":"Ps.139.7.5","verseId":"Ps.139.7"},{"position":6,"surface":"εἶ","lemma":"εἶ","strongs":"1510","morph":{"partOfSpeech":"Verb","casus":null,"number":"Singular","gender":null,"tense":"Present","voice":"Active","mood":"Indicative","person":"2"},"id":"Ps.139.7.6","verseId":"Ps.139.7"},{"position":7,"surface":"σύ","lemma":"σύ","strongs":"4771","morph":{"partOfSpeech":"RP","casus":"Nominative","number":"Singular","tense":null,"voice":null,"mood":null,"person":null},"id":"Ps.139.7.7","verseId":"Ps.139.7"},{"position":8,"surface":"ἐνώτισαι","lemma":"ἐνώτισαι","strongs":"1801","morph":{"partOfSpeech":"Verb","casus":null,"number":"Singular","gender":null,"tense":"Aorist","voice":"Active","mood":"Imperative","person":"2"},"id":"Ps.139.7.8","verseId":"Ps.139.7"},{"position":9,"surface":"κύριε","lemma":"κύριε","strongs":"2962","morph":{"partOfSpeech":"Noun","casus":"Vocative","number":"Singular","gender":"Masculine","tense":null,"voice":null,"mood":null,"person":null},"id":"Ps.139.7.9","verseId":"Ps.139.7"},{"position":10,"surface":"τὴν","lemma":"τὴν","strongs":"3588","morph":{"partOfSpeech":"Article","casus":"Accusative","number":"Singular","gender":"Feminine","tense":null,"voice":null,"mood":null,"person":null},"id":"Ps.139.7.10","verseId":"Ps.139.7"},{"position":11,"surface":"φωνὴν","lemma":"φωνὴν","strongs":"5456","morph":{"partOfSpeech":"Noun","casus":"Accusative","number":"Singular","gender":"Feminine","tense":null,"voice":null,"mood":null,"person":null},"id":"Ps.139.7.11","verseId":"Ps.139.7"},{"position":12,"surface":"τῆς","lemma":"τῆς","strongs":"3588","morph":{"partOfSpeech":"Article","casus":"Genitive","number":"Singular","gender":"Feminine","tense":null,"voice":null,"mood":null,"person":null},"id":"Ps.139.7.12","verseId":"Ps.139.7"},{"position":13,"surface":"δεήσεώς","lemma":"δεήσεώς","strongs":"1162","morph":{"partOfSpeech":"Noun","casus":"Genitive","number":"Singular","gender":"Feminine","tense":null,"voice":null,"mood":null,"person":null},"id":"Ps.139.7.13","verseId":"Ps.139.7"},{"position":14,"surface":"μου","lemma":"μου","strongs":"3450","morph":{"partOfSpeech":"RP","casus":"Genitive","number":"Singular","tense":null,"voice":null,"mood":null,"person":null},"id":"Ps.139.7.14","verseId":"Ps.139.7"}]},{"id":"Ps.139.8","bookId":"Ps","chapter":139,"verse":8,"reference":"Psalms 139:8","text":"κύριε κύριε δύναμις τῆς σωτηρίας μου ἐπεσκίασας ἐπὶ τὴν κεφαλήν μου ἐν ἡμέρᾳ πολέμου","words":[{"position":1,"surface":"κύριε","lemma":"κύριε","strongs":"2962","morph":{"partOfSpeech":"Noun","casus":"Vocative","number":"Singular","gender":"Masculine","tense":null,"voice":null,"mood":null,"person":null},"id":"Ps.139.8.1","verseId":"Ps.139.8"},{"position":2,"surface":"κύριε","lemma":"κύριε","strongs":"2962","morph":{"partOfSpeech":"Noun","casus":"Vocative","number":"Singular","gender":"Masculine","tense":null,"voice":null,"mood":null,"person":null},"id":"Ps.139.8.2","verseId":"Ps.139.8"},{"position":3,"surface":"δύναμις","lemma":"δύναμις","strongs":"1411","morph":{"partOfSpeech":"Noun","casus":"Nominative","number":"Singular","gender":"Feminine","tense":null,"voice":null,"mood":null,"person":null},"id":"Ps.139.8.3","verseId":"Ps.139.8"},{"position":4,"surface":"τῆς","lemma":"τῆς","strongs":"3588","morph":{"partOfSpeech":"Article","casus":"Genitive","number":"Singular","gender":"Feminine","tense":null,"voice":null,"mood":null,"person":null},"id":"Ps.139.8.4","verseId":"Ps.139.8"},{"position":5,"surface":"σωτηρίας","lemma":"σωτηρίας","strongs":"4991","morph":{"partOfSpeech":"Noun","casus":"Genitive","number":"Singular","gender":"Feminine","tense":null,"voice":null,"mood":null,"person":null},"id":"Ps.139.8.5","verseId":"Ps.139.8"},{"position":6,"surface":"μου","lemma":"μου","strongs":"3450","morph":{"partOfSpeech":"RP","casus":"Genitive","number":"Singular","tense":null,"voice":null,"mood":null,"person":null},"id":"Ps.139.8.6","verseId":"Ps.139.8"},{"position":7,"surface":"ἐπεσκίασας","lemma":"ἐπεσκίασας","strongs":"1982","morph":{"partOfSpeech":"Verb","casus":null,"number":"Singular","gender":null,"tense":"Aorist","voice":"Active","mood":"Indicative","person":"2"},"id":"Ps.139.8.7","verseId":"Ps.139.8"},{"position":8,"surface":"ἐπὶ","lemma":"ἐπὶ","strongs":"1909","morph":{"partOfSpeech":"Preposition","casus":null,"number":null,"gender":null,"tense":null,"voice":null,"mood":null,"person":null},"id":"Ps.139.8.8","verseId":"Ps.139.8"},{"position":9,"surface":"τὴν","lemma":"τὴν","strongs":"3588","morph":{"partOfSpeech":"Article","casus":"Accusative","number":"Singular","gender":"Feminine","tense":null,"voice":null,"mood":null,"person":null},"id":"Ps.139.8.9","verseId":"Ps.139.8"},{"position":10,"surface":"κεφαλήν","lemma":"κεφαλήν","strongs":"2776","morph":{"partOfSpeech":"Noun","casus":"Accusative","number":"Singular","gender":"Feminine","tense":null,"voice":null,"mood":null,"person":null},"id":"Ps.139.8.10","verseId":"Ps.139.8"},{"position":11,"surface":"μου","lemma":"μου","strongs":"3450","morph":{"partOfSpeech":"RP","casus":"Genitive","number":"Singular","tense":null,"voice":null,"mood":null,"person":null},"id":"Ps.139.8.11","verseId":"Ps.139.8"},{"position":12,"surface":"ἐν","lemma":"ἐν","strongs":"1722","morph":{"partOfSpeech":"Preposition","casus":null,"number":null,"gender":null,"tense":null,"voice":null,"mood":null,"person":null},"id":"Ps.139.8.12","verseId":"Ps.139.8"},{"position":13,"surface":"ἡμέρᾳ","lemma":"ἡμέρᾳ","strongs":"2250","morph":{"partOfSpeech":"Noun","casus":"Dative","number":"Singular","gender":"Feminine","tense":null,"voice":null,"mood":null,"person":null},"id":"Ps.139.8.13","verseId":"Ps.139.8"},{"position":14,"surface":"πολέμου","lemma":"πολέμου","strongs":"4171","morph":{"partOfSpeech":"Noun","casus":"Genitive","number":"Singular","gender":"Masculine","tense":null,"voice":null,"mood":null,"person":null},"id":"Ps.139.8.14","verseId":"Ps.139.8"}]},{"id":"Ps.139.9","bookId":"Ps","chapter":139,"verse":9,"reference":"Psalms 139:9","text":"μὴ παραδῷς με κύριε ἀπὸ τῆς ἐπιθυμίας μου ἁμαρτωλῷ διελογίσαντο κατ᾿ ἐμοῦ μὴ ἐγκαταλίπῃς με μήποτε ὑψωθῶσιν διάψαλμα","words":[{"position":1,"surface":"μὴ","lemma":"μὴ","strongs":"3361","morph":{"partOfSpeech":"Adverb","casus":null,"number":null,"gender":null,"tense":null,"voice":null,"mood":null,"person":null},"id":"Ps.139.9.1","verseId":"Ps.139.9"},{"position":2,"surface":"παραδῷς","lemma":"παραδῷς","strongs":"3860","morph":{"partOfSpeech":"Verb","casus":null,"number":"Singular","gender":null,"tense":"Aorist","voice":"Active","mood":"Subjunctive","person":"2"},"id":"Ps.139.9.2","verseId":"Ps.139.9"},{"position":3,"surface":"με","lemma":"με","strongs":"3165","morph":{"partOfSpeech":"RP","casus":"Accusative","number":"Singular","tense":null,"voice":null,"mood":null,"person":null},"id":"Ps.139.9.3","verseId":"Ps.139.9"},{"position":4,"surface":"κύριε","lemma":"κύριε","strongs":"2962","morph":{"partOfSpeech":"Noun","casus":"Vocative","number":"Singular","gender":"Masculine","tense":null,"voice":null,"mood":null,"person":null},"id":"Ps.139.9.4","verseId":"Ps.139.9"},{"position":5,"surface":"ἀπὸ","lemma":"ἀπὸ","strongs":"575","morph":{"partOfSpeech":"Preposition","casus":null,"number":null,"gender":null,"tense":null,"voice":null,"mood":null,"person":null},"id":"Ps.139.9.5","verseId":"Ps.139.9"},{"position":6,"surface":"τῆς","lemma":"τῆς","strongs":"3588","morph":{"partOfSpeech":"Article","casus":"Genitive","number":"Singular","gender":"Feminine","tense":null,"voice":null,"mood":null,"person":null},"id":"Ps.139.9.6","verseId":"Ps.139.9"},{"position":7,"surface":"ἐπιθυμίας","lemma":"ἐπιθυμίας","strongs":"1939","morph":{"partOfSpeech":"Noun","casus":"Genitive","number":"Singular","gender":"Feminine","tense":null,"voice":null,"mood":null,"person":null},"id":"Ps.139.9.7","verseId":"Ps.139.9"},{"position":8,"surface":"μου","lemma":"μου","strongs":"3450","morph":{"partOfSpeech":"RP","casus":"Genitive","number":"Singular","tense":null,"voice":null,"mood":null,"person":null},"id":"Ps.139.9.8","verseId":"Ps.139.9"},{"position":9,"surface":"ἁμαρτωλῷ","lemma":"ἁμαρτωλῷ","strongs":"268","morph":{"partOfSpeech":"Adjective","casus":"Dative","number":"Singular","gender":"Masculine","tense":null,"voice":null,"mood":null,"person":null},"id":"Ps.139.9.9","verseId":"Ps.139.9"},{"position":10,"surface":"διελογίσαντο","lemma":"διελογίσαντο","strongs":"1260","morph":{"partOfSpeech":"Verb","casus":null,"number":"Plural","gender":null,"tense":"Aorist","voice":"Middle","mood":"Indicative","person":"3"},"id":"Ps.139.9.10","verseId":"Ps.139.9"},{"position":11,"surface":"κατ᾿","lemma":"κατ᾿","strongs":"2596","morph":{"partOfSpeech":"Preposition","casus":null,"number":null,"gender":null,"tense":null,"voice":null,"mood":null,"person":null},"id":"Ps.139.9.11","verseId":"Ps.139.9"},{"position":12,"surface":"ἐμοῦ","lemma":"ἐμοῦ","strongs":"1700","morph":{"partOfSpeech":"RP","casus":"Genitive","number":"Singular","tense":null,"voice":null,"mood":null,"person":null},"id":"Ps.139.9.12","verseId":"Ps.139.9"},{"position":13,"surface":"μὴ","lemma":"μὴ","strongs":"3361","morph":{"partOfSpeech":"Adverb","casus":null,"number":null,"gender":null,"tense":null,"voice":null,"mood":null,"person":null},"id":"Ps.139.9.13","verseId":"Ps.139.9"},{"position":14,"surface":"ἐγκαταλίπῃς","lemma":"ἐγκαταλίπῃς","strongs":"1459","morph":{"partOfSpeech":"Verb","casus":null,"number":"Singular","gender":null,"tense":"Aorist","voice":"Active","mood":"Subjunctive","person":"2"},"id":"Ps.139.9.14","verseId":"Ps.139.9"},{"position":15,"surface":"με","lemma":"με","strongs":"3165","morph":{"partOfSpeech":"RP","casus":"Accusative","number":"Singular","tense":null,"voice":null,"mood":null,"person":null},"id":"Ps.139.9.15","verseId":"Ps.139.9"},{"position":16,"surface":"μήποτε","lemma":"μήποτε","strongs":"3379","morph":{"partOfSpeech":"Adverb","casus":null,"number":null,"gender":null,"tense":null,"voice":null,"mood":null,"person":null},"id":"Ps.139.9.16","verseId":"Ps.139.9"},{"position":17,"surface":"ὑψωθῶσιν","lemma":"ὑψωθῶσιν","strongs":"5312","morph":{"partOfSpeech":"Verb","casus":null,"number":"Plural","gender":null,"tense":"Aorist","voice":"Passive","mood":"Subjunctive","person":"3"},"id":"Ps.139.9.17","verseId":"Ps.139.9"},{"position":18,"surface":"διάψαλμα","lemma":"διάψαλμα","strongs":"","morph":{"partOfSpeech":"Noun","casus":"Nominative","number":"Singular","gender":"Neuter","tense":null,"voice":null,"mood":null,"person":null},"id":"Ps.139.9.18","verseId":"Ps.139.9"}]},{"id":"Ps.139.10","bookId":"Ps","chapter":139,"verse":10,"reference":"Psalms 139:10","text":"ἡ κεφαλὴ τοῦ κυκλώματος αὐτῶν κόπος τῶν χειλέων αὐτῶν καλύψει αὐτούς","words":[{"position":1,"surface":"ἡ","lemma":"ἡ","strongs":"3588","morph":{"partOfSpeech":"Article","casus":"Nominative","number":"Singular","gender":"Feminine","tense":null,"voice":null,"mood":null,"person":null},"id":"Ps.139.10.1","verseId":"Ps.139.10"},{"position":2,"surface":"κεφαλὴ","lemma":"κεφαλὴ","strongs":"2776","morph":{"partOfSpeech":"Noun","casus":"Nominative","number":"Singular","gender":"Feminine","tense":null,"voice":null,"mood":null,"person":null},"id":"Ps.139.10.2","verseId":"Ps.139.10"},{"position":3,"surface":"τοῦ","lemma":"τοῦ","strongs":"3588","morph":{"partOfSpeech":"Article","casus":"Genitive","number":"Singular","gender":"Neuter","tense":null,"voice":null,"mood":null,"person":null},"id":"Ps.139.10.3","verseId":"Ps.139.10"},{"position":4,"surface":"κυκλώματος","lemma":"κυκλώματος","strongs":"","morph":{"partOfSpeech":"Noun","casus":"Genitive","number":"Singular","gender":"Neuter","tense":null,"voice":null,"mood":null,"person":null},"id":"Ps.139.10.4","verseId":"Ps.139.10"},{"position":5,"surface":"αὐτῶν","lemma":"αὐτῶν","strongs":"846","morph":{"partOfSpeech":"RP","casus":"Genitive","number":"Plural","gender":"Masculine","tense":null,"voice":null,"mood":null,"person":null},"id":"Ps.139.10.5","verseId":"Ps.139.10"},{"position":6,"surface":"κόπος","lemma":"κόπος","strongs":"2873","morph":{"partOfSpeech":"Noun","casus":"Nominative","number":"Singular","gender":"Masculine","tense":null,"voice":null,"mood":null,"person":null},"id":"Ps.139.10.6","verseId":"Ps.139.10"},{"position":7,"surface":"τῶν","lemma":"τῶν","strongs":"3588","morph":{"partOfSpeech":"Article","casus":"Genitive","number":"Plural","gender":"Neuter","tense":null,"voice":null,"mood":null,"person":null},"id":"Ps.139.10.7","verseId":"Ps.139.10"},{"position":8,"surface":"χειλέων","lemma":"χειλέων","strongs":"5491","morph":{"partOfSpeech":"Noun","casus":"Genitive","number":"Plural","gender":"Neuter","tense":null,"voice":null,"mood":null,"person":null},"id":"Ps.139.10.8","verseId":"Ps.139.10"},{"position":9,"surface":"αὐτῶν","lemma":"αὐτῶν","strongs":"846","morph":{"partOfSpeech":"RP","casus":"Genitive","number":"Plural","gender":"Masculine","tense":null,"voice":null,"mood":null,"person":null},"id":"Ps.139.10.9","verseId":"Ps.139.10"},{"position":10,"surface":"καλύψει","lemma":"καλύψει","strongs":"2572","morph":{"partOfSpeech":"Verb","casus":null,"number":"Singular","gender":null,"tense":"Future","voice":"Active","mood":"Indicative","person":"3"},"id":"Ps.139.10.10","verseId":"Ps.139.10"},{"position":11,"surface":"αὐτούς","lemma":"αὐτούς","strongs":"846","morph":{"partOfSpeech":"RP","casus":"Accusative","number":"Plural","gender":"Masculine","tense":null,"voice":null,"mood":null,"person":null},"id":"Ps.139.10.11","verseId":"Ps.139.10"}]},{"id":"Ps.139.11","bookId":"Ps","chapter":139,"verse":11,"reference":"Psalms 139:11","text":"πεσοῦνται ἐπ᾿ αὐτοὺς ἄνθρακες ἐν πυρὶ καταβαλεῖς αὐτούς ἐν ταλαιπωρίαις οὐ μὴ ὑποστῶσιν","words":[{"position":1,"surface":"πεσοῦνται","lemma":"πεσοῦνται","strongs":"4098","morph":{"partOfSpeech":"Verb","casus":null,"number":"Plural","gender":null,"tense":"Future","voice":"Middle","mood":"Indicative","person":"3"},"id":"Ps.139.11.1","verseId":"Ps.139.11"},{"position":2,"surface":"ἐπ᾿","lemma":"ἐπ᾿","strongs":"1909","morph":{"partOfSpeech":"Preposition","casus":null,"number":null,"gender":null,"tense":null,"voice":null,"mood":null,"person":null},"id":"Ps.139.11.2","verseId":"Ps.139.11"},{"position":3,"surface":"αὐτοὺς","lemma":"αὐτοὺς","strongs":"846","morph":{"partOfSpeech":"RP","casus":"Accusative","number":"Plural","gender":"Masculine","tense":null,"voice":null,"mood":null,"person":null},"id":"Ps.139.11.3","verseId":"Ps.139.11"},{"position":4,"surface":"ἄνθρακες","lemma":"ἄνθρακες","strongs":"440","morph":{"partOfSpeech":"Noun","casus":"Nominative","number":"Plural","gender":"Masculine","tense":null,"voice":null,"mood":null,"person":null},"id":"Ps.139.11.4","verseId":"Ps.139.11"},{"position":5,"surface":"ἐν","lemma":"ἐν","strongs":"1722","morph":{"partOfSpeech":"Preposition","casus":null,"number":null,"gender":null,"tense":null,"voice":null,"mood":null,"person":null},"id":"Ps.139.11.5","verseId":"Ps.139.11"},{"position":6,"surface":"πυρὶ","lemma":"πυρὶ","strongs":"4442","morph":{"partOfSpeech":"Noun","casus":"Dative","number":"Singular","gender":"Neuter","tense":null,"voice":null,"mood":null,"person":null},"id":"Ps.139.11.6","verseId":"Ps.139.11"},{"position":7,"surface":"καταβαλεῖς","lemma":"καταβαλεῖς","strongs":"2598","morph":{"partOfSpeech":"Verb","casus":null,"number":"Singular","gender":null,"tense":"Future","voice":"Active","mood":"Indicative","person":"2"},"id":"Ps.139.11.7","verseId":"Ps.139.11"},{"position":8,"surface":"αὐτούς","lemma":"αὐτούς","strongs":"846","morph":{"partOfSpeech":"RP","casus":"Accusative","number":"Plural","gender":"Masculine","tense":null,"voice":null,"mood":null,"person":null},"id":"Ps.139.11.8","verseId":"Ps.139.11"},{"position":9,"surface":"ἐν","lemma":"ἐν","strongs":"1722","morph":{"partOfSpeech":"Preposition","casus":null,"number":null,"gender":null,"tense":null,"voice":null,"mood":null,"person":null},"id":"Ps.139.11.9","verseId":"Ps.139.11"},{"position":10,"surface":"ταλαιπωρίαις","lemma":"ταλαιπωρίαις","strongs":"5004","morph":{"partOfSpeech":"Noun","casus":"Dative","number":"Plural","gender":"Feminine","tense":null,"voice":null,"mood":null,"person":null},"id":"Ps.139.11.10","verseId":"Ps.139.11"},{"position":11,"surface":"οὐ","lemma":"οὐ","strongs":"3756","morph":{"partOfSpeech":"Adverb","casus":null,"number":null,"gender":null,"tense":null,"voice":null,"mood":null,"person":null},"id":"Ps.139.11.11","verseId":"Ps.139.11"},{"position":12,"surface":"μὴ","lemma":"μὴ","strongs":"3361","morph":{"partOfSpeech":"Adverb","casus":null,"number":null,"gender":null,"tense":null,"voice":null,"mood":null,"person":null},"id":"Ps.139.11.12","verseId":"Ps.139.11"},{"position":13,"surface":"ὑποστῶσιν","lemma":"ὑποστῶσιν","strongs":"","morph":{"partOfSpeech":"Verb","casus":null,"number":"Plural","gender":null,"tense":"Aorist","voice":"Active","mood":"Subjunctive","person":"3"},"id":"Ps.139.11.13","verseId":"Ps.139.11"}]},{"id":"Ps.139.12","bookId":"Ps","chapter":139,"verse":12,"reference":"Psalms 139:12","text":"ἀνὴρ γλωσσώδης οὐ κατευθυνθήσεται ἐπὶ τῆς γῆς ἄνδρα ἄδικον κακὰ θηρεύσει εἰς διαφθοράν","words":[{"position":1,"surface":"ἀνὴρ","lemma":"ἀνὴρ","strongs":"435","morph":{"partOfSpeech":"Noun","casus":"Nominative","number":"Singular","gender":"Masculine","tense":null,"voice":null,"mood":null,"person":null},"id":"Ps.139.12.1","verseId":"Ps.139.12"},{"position":2,"surface":"γλωσσώδης","lemma":"γλωσσώδης","strongs":"","morph":{"partOfSpeech":"Adjective","casus":"Nominative","number":"Singular","gender":"Masculine","tense":null,"voice":null,"mood":null,"person":null},"id":"Ps.139.12.2","verseId":"Ps.139.12"},{"position":3,"surface":"οὐ","lemma":"οὐ","strongs":"3756","morph":{"partOfSpeech":"Adverb","casus":null,"number":null,"gender":null,"tense":null,"voice":null,"mood":null,"person":null},"id":"Ps.139.12.3","verseId":"Ps.139.12"},{"position":4,"surface":"κατευθυνθήσεται","lemma":"κατευθυνθήσεται","strongs":"2720","morph":{"partOfSpeech":"Verb","casus":null,"number":"Singular","gender":null,"tense":"Future","voice":"Passive","mood":"Indicative","person":"3"},"id":"Ps.139.12.4","verseId":"Ps.139.12"},{"position":5,"surface":"ἐπὶ","lemma":"ἐπὶ","strongs":"1909","morph":{"partOfSpeech":"Preposition","casus":null,"number":null,"gender":null,"tense":null,"voice":null,"mood":null,"person":null},"id":"Ps.139.12.5","verseId":"Ps.139.12"},{"position":6,"surface":"τῆς","lemma":"τῆς","strongs":"3588","morph":{"partOfSpeech":"Article","casus":"Genitive","number":"Singular","gender":"Feminine","tense":null,"voice":null,"mood":null,"person":null},"id":"Ps.139.12.6","verseId":"Ps.139.12"},{"position":7,"surface":"γῆς","lemma":"γῆς","strongs":"1093","morph":{"partOfSpeech":"Noun","casus":"Genitive","number":"Singular","gender":"Feminine","tense":null,"voice":null,"mood":null,"person":null},"id":"Ps.139.12.7","verseId":"Ps.139.12"},{"position":8,"surface":"ἄνδρα","lemma":"ἄνδρα","strongs":"435","morph":{"partOfSpeech":"Noun","casus":"Accusative","number":"Singular","gender":"Masculine","tense":null,"voice":null,"mood":null,"person":null},"id":"Ps.139.12.8","verseId":"Ps.139.12"},{"position":9,"surface":"ἄδικον","lemma":"ἄδικον","strongs":"94","morph":{"partOfSpeech":"Adjective","casus":"Accusative","number":"Singular","gender":"Masculine","tense":null,"voice":null,"mood":null,"person":null},"id":"Ps.139.12.9","verseId":"Ps.139.12"},{"position":10,"surface":"κακὰ","lemma":"κακὰ","strongs":"2556","morph":{"partOfSpeech":"Adjective","casus":"Nominative","number":"Plural","gender":"Neuter","tense":null,"voice":null,"mood":null,"person":null},"id":"Ps.139.12.10","verseId":"Ps.139.12"},{"position":11,"surface":"θηρεύσει","lemma":"θηρεύσει","strongs":"","morph":{"partOfSpeech":"Verb","casus":null,"number":"Singular","gender":null,"tense":"Future","voice":"Active","mood":"Indicative","person":"3"},"id":"Ps.139.12.11","verseId":"Ps.139.12"},{"position":12,"surface":"εἰς","lemma":"εἰς","strongs":"1519","morph":{"partOfSpeech":"Preposition","casus":null,"number":null,"gender":null,"tense":null,"voice":null,"mood":null,"person":null},"id":"Ps.139.12.12","verseId":"Ps.139.12"},{"position":13,"surface":"διαφθοράν","lemma":"διαφθοράν","strongs":"1312","morph":{"partOfSpeech":"Noun","casus":"Accusative","number":"Singular","gender":"Feminine","tense":null,"voice":null,"mood":null,"person":null},"id":"Ps.139.12.13","verseId":"Ps.139.12"}]},{"id":"Ps.139.13","bookId":"Ps","chapter":139,"verse":13,"reference":"Psalms 139:13","text":"ἔγνων ὅτι ποιήσει κύριος τὴν κρίσιν τοῦ πτωχοῦ καὶ τὴν δίκην τῶν πενήτων","words":[{"position":1,"surface":"ἔγνων","lemma":"ἔγνων","strongs":"1097","morph":{"partOfSpeech":"Verb","casus":null,"number":"Singular","gender":null,"tense":"Aorist","voice":"Active","mood":"Indicative","person":"1"},"id":"Ps.139.13.1","verseId":"Ps.139.13"},{"position":2,"surface":"ὅτι","lemma":"ὅτι","strongs":"3754","morph":{"partOfSpeech":"Conjunction","casus":null,"number":null,"gender":null,"tense":null,"voice":null,"mood":null,"person":null},"id":"Ps.139.13.2","verseId":"Ps.139.13"},{"position":3,"surface":"ποιήσει","lemma":"ποιήσει","strongs":"4160","morph":{"partOfSpeech":"Verb","casus":null,"number":"Singular","gender":null,"tense":"Future","voice":"Active","mood":"Indicative","person":"3"},"id":"Ps.139.13.3","verseId":"Ps.139.13"},{"position":4,"surface":"κύριος","lemma":"κύριος","strongs":"2962","morph":{"partOfSpeech":"Noun","casus":"Nominative","number":"Singular","gender":"Masculine","tense":null,"voice":null,"mood":null,"person":null},"id":"Ps.139.13.4","verseId":"Ps.139.13"},{"position":5,"surface":"τὴν","lemma":"τὴν","strongs":"3588","morph":{"partOfSpeech":"Article","casus":"Accusative","number":"Singular","gender":"Feminine","tense":null,"voice":null,"mood":null,"person":null},"id":"Ps.139.13.5","verseId":"Ps.139.13"},{"position":6,"surface":"κρίσιν","lemma":"κρίσιν","strongs":"2920","morph":{"partOfSpeech":"Noun","casus":"Accusative","number":"Singular","gender":"Feminine","tense":null,"voice":null,"mood":null,"person":null},"id":"Ps.139.13.6","verseId":"Ps.139.13"},{"position":7,"surface":"τοῦ","lemma":"τοῦ","strongs":"3588","morph":{"partOfSpeech":"Article","casus":"Genitive","number":"Singular","gender":"Masculine","tense":null,"voice":null,"mood":null,"person":null},"id":"Ps.139.13.7","verseId":"Ps.139.13"},{"position":8,"surface":"πτωχοῦ","lemma":"πτωχοῦ","strongs":"4434","morph":{"partOfSpeech":"Noun","casus":"Genitive","number":"Singular","gender":"Masculine","tense":null,"voice":null,"mood":null,"person":null},"id":"Ps.139.13.8","verseId":"Ps.139.13"},{"position":9,"surface":"καὶ","lemma":"καὶ","strongs":"2532","morph":{"partOfSpeech":"Conjunction","casus":null,"number":null,"gender":null,"tense":null,"voice":null,"mood":null,"person":null},"id":"Ps.139.13.9","verseId":"Ps.139.13"},{"position":10,"surface":"τὴν","lemma":"τὴν","strongs":"3588","morph":{"partOfSpeech":"Article","casus":"Accusative","number":"Singular","gender":"Feminine","tense":null,"voice":null,"mood":null,"person":null},"id":"Ps.139.13.10","verseId":"Ps.139.13"},{"position":11,"surface":"δίκην","lemma":"δίκην","strongs":"1349","morph":{"partOfSpeech":"Noun","casus":"Accusative","number":"Singular","gender":"Feminine","tense":null,"voice":null,"mood":null,"person":null},"id":"Ps.139.13.11","verseId":"Ps.139.13"},{"position":12,"surface":"τῶν","lemma":"τῶν","strongs":"3588","morph":{"partOfSpeech":"Article","casus":"Genitive","number":"Plural","gender":"Masculine","tense":null,"voice":null,"mood":null,"person":null},"id":"Ps.139.13.12","verseId":"Ps.139.13"},{"position":13,"surface":"πενήτων","lemma":"πενήτων","strongs":"3993","morph":{"partOfSpeech":"Noun","casus":"Genitive","number":"Plural","gender":"Masculine","tense":null,"voice":null,"mood":null,"person":null},"id":"Ps.139.13.13","verseId":"Ps.139.13"}]},{"id":"Ps.139.14","bookId":"Ps","chapter":139,"verse":14,"reference":"Psalms 139:14","text":"πλὴν δίκαιοι ἐξομολογήσονται τῷ ὀνόματί σου καὶ κατοικήσουσιν εὐθεῖς σὺν τῷ προσώπῳ σου","words":[{"position":1,"surface":"πλὴν","lemma":"πλὴν","strongs":"4133","morph":{"partOfSpeech":"Adverb","casus":null,"number":null,"gender":null,"tense":null,"voice":null,"mood":null,"person":null},"id":"Ps.139.14.1","verseId":"Ps.139.14"},{"position":2,"surface":"δίκαιοι","lemma":"δίκαιοι","strongs":"1342","morph":{"partOfSpeech":"Adjective","casus":"Nominative","number":"Plural","gender":"Masculine","tense":null,"voice":null,"mood":null,"person":null},"id":"Ps.139.14.2","verseId":"Ps.139.14"},{"position":3,"surface":"ἐξομολογήσονται","lemma":"ἐξομολογήσονται","strongs":"1843","morph":{"partOfSpeech":"Verb","casus":null,"number":"Plural","gender":null,"tense":"Future","voice":"Middle","mood":"Indicative","person":"3"},"id":"Ps.139.14.3","verseId":"Ps.139.14"},{"position":4,"surface":"τῷ","lemma":"τῷ","strongs":"3588","morph":{"partOfSpeech":"Article","casus":"Dative","number":"Singular","gender":"Neuter","tense":null,"voice":null,"mood":null,"person":null},"id":"Ps.139.14.4","verseId":"Ps.139.14"},{"position":5,"surface":"ὀνόματί","lemma":"ὀνόματί","strongs":"3686","morph":{"partOfSpeech":"Noun","casus":"Dative","number":"Singular","gender":"Neuter","tense":null,"voice":null,"mood":null,"person":null},"id":"Ps.139.14.5","verseId":"Ps.139.14"},{"position":6,"surface":"σου","lemma":"σου","strongs":"4675","morph":{"partOfSpeech":"RP","casus":"Genitive","number":"Singular","tense":null,"voice":null,"mood":null,"person":null},"id":"Ps.139.14.6","verseId":"Ps.139.14"},{"position":7,"surface":"καὶ","lemma":"καὶ","strongs":"2532","morph":{"partOfSpeech":"Conjunction","casus":null,"number":null,"gender":null,"tense":null,"voice":null,"mood":null,"person":null},"id":"Ps.139.14.7","verseId":"Ps.139.14"},{"position":8,"surface":"κατοικήσουσιν","lemma":"κατοικήσουσιν","strongs":"2730","morph":{"partOfSpeech":"Verb","casus":null,"number":"Plural","gender":null,"tense":"Future","voice":"Active","mood":"Indicative","person":"3"},"id":"Ps.139.14.8","verseId":"Ps.139.14"},{"position":9,"surface":"εὐθεῖς","lemma":"εὐθεῖς","strongs":"2117","morph":{"partOfSpeech":"Adjective","casus":"Nominative","number":"Plural","gender":"Masculine","tense":null,"voice":null,"mood":null,"person":null},"id":"Ps.139.14.9","verseId":"Ps.139.14"},{"position":10,"surface":"σὺν","lemma":"σὺν","strongs":"4862","morph":{"partOfSpeech":"Preposition","casus":null,"number":null,"gender":null,"tense":null,"voice":null,"mood":null,"person":null},"id":"Ps.139.14.10","verseId":"Ps.139.14"},{"position":11,"surface":"τῷ","lemma":"τῷ","strongs":"3588","morph":{"partOfSpeech":"Article","casus":"Dative","number":"Singular","gender":"Neuter","tense":null,"voice":null,"mood":null,"person":null},"id":"Ps.139.14.11","verseId":"Ps.139.14"},{"position":12,"surface":"προσώπῳ","lemma":"προσώπῳ","strongs":"4383","morph":{"partOfSpeech":"Noun","casus":"Dative","number":"Singular","gender":"Neuter","tense":null,"voice":null,"mood":null,"person":null},"id":"Ps.139.14.12","verseId":"Ps.139.14"},{"position":13,"surface":"σου","lemma":"σου","strongs":"4675","morph":{"partOfSpeech":"RP","casus":"Genitive","number":"Singular","tense":null,"voice":null,"mood":null,"person":null},"id":"Ps.139.14.13","verseId":"Ps.139.14"}]}]}