{"book":"Ps","chapter":31,"verses":[{"id":"Ps.31.1","bookId":"Ps","chapter":31,"verse":1,"reference":"Psalms 31:1","text":"τῷ Δαυιδ συνέσεως μακάριοι ὧν ἀφέθησαν αἱ ἀνομίαι καὶ ὧν ἐπεκαλύφθησαν αἱ ἁμαρτίαι","words":[{"position":1,"surface":"τῷ","lemma":"τῷ","strongs":"3588","morph":{"partOfSpeech":"Article","casus":"Dative","number":"Singular","gender":"Masculine","tense":null,"voice":null,"mood":null,"person":null},"id":"Ps.31.1.1","verseId":"Ps.31.1"},{"position":2,"surface":"Δαυιδ","lemma":"Δαυιδ","strongs":"1138","morph":{"partOfSpeech":"Noun","casus":"Dative","number":"Singular","gender":"Masculine","tense":null,"voice":null,"mood":null,"person":null},"id":"Ps.31.1.2","verseId":"Ps.31.1"},{"position":3,"surface":"συνέσεως","lemma":"συνέσεως","strongs":"4907","morph":{"partOfSpeech":"Noun","casus":"Genitive","number":"Singular","gender":"Feminine","tense":null,"voice":null,"mood":null,"person":null},"id":"Ps.31.1.3","verseId":"Ps.31.1"},{"position":4,"surface":"μακάριοι","lemma":"μακάριοι","strongs":"3107","morph":{"partOfSpeech":"Adjective","casus":"Nominative","number":"Plural","gender":"Masculine","tense":null,"voice":null,"mood":null,"person":null},"id":"Ps.31.1.4","verseId":"Ps.31.1"},{"position":5,"surface":"ὧν","lemma":"ὧν","strongs":"3739","morph":{"partOfSpeech":"Relative Pronoun","casus":"Genitive","number":"Plural","gender":"Masculine","tense":null,"voice":null,"mood":null,"person":null},"id":"Ps.31.1.5","verseId":"Ps.31.1"},{"position":6,"surface":"ἀφέθησαν","lemma":"ἀφέθησαν","strongs":"863","morph":{"partOfSpeech":"Verb","casus":null,"number":"Plural","gender":null,"tense":"Aorist","voice":"Passive","mood":"Indicative","person":"3"},"id":"Ps.31.1.6","verseId":"Ps.31.1"},{"position":7,"surface":"αἱ","lemma":"αἱ","strongs":"3588","morph":{"partOfSpeech":"Article","casus":"Nominative","number":"Plural","gender":"Feminine","tense":null,"voice":null,"mood":null,"person":null},"id":"Ps.31.1.7","verseId":"Ps.31.1"},{"position":8,"surface":"ἀνομίαι","lemma":"ἀνομίαι","strongs":"458","morph":{"partOfSpeech":"Noun","casus":"Nominative","number":"Plural","gender":"Feminine","tense":null,"voice":null,"mood":null,"person":null},"id":"Ps.31.1.8","verseId":"Ps.31.1"},{"position":9,"surface":"καὶ","lemma":"καὶ","strongs":"2532","morph":{"partOfSpeech":"Conjunction","casus":null,"number":null,"gender":null,"tense":null,"voice":null,"mood":null,"person":null},"id":"Ps.31.1.9","verseId":"Ps.31.1"},{"position":10,"surface":"ὧν","lemma":"ὧν","strongs":"3739","morph":{"partOfSpeech":"Relative Pronoun","casus":"Genitive","number":"Plural","gender":"Masculine","tense":null,"voice":null,"mood":null,"person":null},"id":"Ps.31.1.10","verseId":"Ps.31.1"},{"position":11,"surface":"ἐπεκαλύφθησαν","lemma":"ἐπεκαλύφθησαν","strongs":"1943","morph":{"partOfSpeech":"Verb","casus":null,"number":"Plural","gender":null,"tense":"Aorist","voice":"Passive","mood":"Indicative","person":"3"},"id":"Ps.31.1.11","verseId":"Ps.31.1"},{"position":12,"surface":"αἱ","lemma":"αἱ","strongs":"3588","morph":{"partOfSpeech":"Article","casus":"Nominative","number":"Plural","gender":"Feminine","tense":null,"voice":null,"mood":null,"person":null},"id":"Ps.31.1.12","verseId":"Ps.31.1"},{"position":13,"surface":"ἁμαρτίαι","lemma":"ἁμαρτίαι","strongs":"266","morph":{"partOfSpeech":"Noun","casus":"Nominative","number":"Plural","gender":"Feminine","tense":null,"voice":null,"mood":null,"person":null},"id":"Ps.31.1.13","verseId":"Ps.31.1"}]},{"id":"Ps.31.2","bookId":"Ps","chapter":31,"verse":2,"reference":"Psalms 31:2","text":"μακάριος ἀνήρ οὗ οὐ μὴ λογίσηται κύριος ἁμαρτίαν οὐδὲ ἔστιν ἐν τῷ στόματι αὐτοῦ δόλος","words":[{"position":1,"surface":"μακάριος","lemma":"μακάριος","strongs":"3107","morph":{"partOfSpeech":"Adjective","casus":"Nominative","number":"Singular","gender":"Masculine","tense":null,"voice":null,"mood":null,"person":null},"id":"Ps.31.2.1","verseId":"Ps.31.2"},{"position":2,"surface":"ἀνήρ","lemma":"ἀνήρ","strongs":"435","morph":{"partOfSpeech":"Noun","casus":"Nominative","number":"Singular","gender":"Masculine","tense":null,"voice":null,"mood":null,"person":null},"id":"Ps.31.2.2","verseId":"Ps.31.2"},{"position":3,"surface":"οὗ","lemma":"οὗ","strongs":"3739","morph":{"partOfSpeech":"Relative Pronoun","casus":"Genitive","number":"Singular","gender":"Masculine","tense":null,"voice":null,"mood":null,"person":null},"id":"Ps.31.2.3","verseId":"Ps.31.2"},{"position":4,"surface":"οὐ","lemma":"οὐ","strongs":"3756","morph":{"partOfSpeech":"Adverb","casus":null,"number":null,"gender":null,"tense":null,"voice":null,"mood":null,"person":null},"id":"Ps.31.2.4","verseId":"Ps.31.2"},{"position":5,"surface":"μὴ","lemma":"μὴ","strongs":"3361","morph":{"partOfSpeech":"Adverb","casus":null,"number":null,"gender":null,"tense":null,"voice":null,"mood":null,"person":null},"id":"Ps.31.2.5","verseId":"Ps.31.2"},{"position":6,"surface":"λογίσηται","lemma":"λογίσηται","strongs":"3049","morph":{"partOfSpeech":"Verb","casus":null,"number":"Singular","gender":null,"tense":"Aorist","voice":"Middle","mood":"Subjunctive","person":"3"},"id":"Ps.31.2.6","verseId":"Ps.31.2"},{"position":7,"surface":"κύριος","lemma":"κύριος","strongs":"2962","morph":{"partOfSpeech":"Noun","casus":"Nominative","number":"Singular","gender":"Masculine","tense":null,"voice":null,"mood":null,"person":null},"id":"Ps.31.2.7","verseId":"Ps.31.2"},{"position":8,"surface":"ἁμαρτίαν","lemma":"ἁμαρτίαν","strongs":"266","morph":{"partOfSpeech":"Noun","casus":"Accusative","number":"Singular","gender":"Feminine","tense":null,"voice":null,"mood":null,"person":null},"id":"Ps.31.2.8","verseId":"Ps.31.2"},{"position":9,"surface":"οὐδὲ","lemma":"οὐδὲ","strongs":"3761","morph":{"partOfSpeech":"Conjunction","casus":null,"number":null,"gender":null,"tense":null,"voice":null,"mood":null,"person":null},"id":"Ps.31.2.9","verseId":"Ps.31.2"},{"position":10,"surface":"ἔστιν","lemma":"ἔστιν","strongs":"1510","morph":{"partOfSpeech":"Verb","casus":null,"number":"Singular","gender":null,"tense":"Present","voice":"Active","mood":"Indicative","person":"3"},"id":"Ps.31.2.10","verseId":"Ps.31.2"},{"position":11,"surface":"ἐν","lemma":"ἐν","strongs":"1722","morph":{"partOfSpeech":"Preposition","casus":null,"number":null,"gender":null,"tense":null,"voice":null,"mood":null,"person":null},"id":"Ps.31.2.11","verseId":"Ps.31.2"},{"position":12,"surface":"τῷ","lemma":"τῷ","strongs":"3588","morph":{"partOfSpeech":"Article","casus":"Dative","number":"Singular","gender":"Neuter","tense":null,"voice":null,"mood":null,"person":null},"id":"Ps.31.2.12","verseId":"Ps.31.2"},{"position":13,"surface":"στόματι","lemma":"στόματι","strongs":"4750","morph":{"partOfSpeech":"Noun","casus":"Dative","number":"Singular","gender":"Neuter","tense":null,"voice":null,"mood":null,"person":null},"id":"Ps.31.2.13","verseId":"Ps.31.2"},{"position":14,"surface":"αὐτοῦ","lemma":"αὐτοῦ","strongs":"846","morph":{"partOfSpeech":"Demonstrative","casus":"Genitive","number":"Singular","gender":"Masculine","tense":null,"voice":null,"mood":null,"person":null},"id":"Ps.31.2.14","verseId":"Ps.31.2"},{"position":15,"surface":"δόλος","lemma":"δόλος","strongs":"1388","morph":{"partOfSpeech":"Noun","casus":"Nominative","number":"Singular","gender":"Masculine","tense":null,"voice":null,"mood":null,"person":null},"id":"Ps.31.2.15","verseId":"Ps.31.2"}]},{"id":"Ps.31.3","bookId":"Ps","chapter":31,"verse":3,"reference":"Psalms 31:3","text":"ὅτι ἐσίγησα ἐπαλαιώθη τὰ ὀστᾶ μου ἀπὸ τοῦ κράζειν με ὅλην τὴν ἡμέραν","words":[{"position":1,"surface":"ὅτι","lemma":"ὅτι","strongs":"3754","morph":{"partOfSpeech":"Conjunction","casus":null,"number":null,"gender":null,"tense":null,"voice":null,"mood":null,"person":null},"id":"Ps.31.3.1","verseId":"Ps.31.3"},{"position":2,"surface":"ἐσίγησα","lemma":"ἐσίγησα","strongs":"4601","morph":{"partOfSpeech":"Verb","casus":null,"number":"Singular","gender":null,"tense":"Aorist","voice":"Active","mood":"Indicative","person":"1"},"id":"Ps.31.3.2","verseId":"Ps.31.3"},{"position":3,"surface":"ἐπαλαιώθη","lemma":"ἐπαλαιώθη","strongs":"3822","morph":{"partOfSpeech":"Verb","casus":null,"number":"Singular","gender":null,"tense":"Aorist","voice":"Passive","mood":"Indicative","person":"3"},"id":"Ps.31.3.3","verseId":"Ps.31.3"},{"position":4,"surface":"τὰ","lemma":"τὰ","strongs":"3588","morph":{"partOfSpeech":"Article","casus":"Nominative","number":"Plural","gender":"Neuter","tense":null,"voice":null,"mood":null,"person":null},"id":"Ps.31.3.4","verseId":"Ps.31.3"},{"position":5,"surface":"ὀστᾶ","lemma":"ὀστᾶ","strongs":"3747","morph":{"partOfSpeech":"Noun","casus":"Nominative","number":"Plural","gender":"Neuter","tense":null,"voice":null,"mood":null,"person":null},"id":"Ps.31.3.5","verseId":"Ps.31.3"},{"position":6,"surface":"μου","lemma":"μου","strongs":"3450","morph":{"partOfSpeech":"RP","casus":"Genitive","number":"Singular","tense":null,"voice":null,"mood":null,"person":null},"id":"Ps.31.3.6","verseId":"Ps.31.3"},{"position":7,"surface":"ἀπὸ","lemma":"ἀπὸ","strongs":"575","morph":{"partOfSpeech":"Preposition","casus":null,"number":null,"gender":null,"tense":null,"voice":null,"mood":null,"person":null},"id":"Ps.31.3.7","verseId":"Ps.31.3"},{"position":8,"surface":"τοῦ","lemma":"τοῦ","strongs":"3588","morph":{"partOfSpeech":"Article","casus":"Genitive","number":"Singular","gender":"Neuter","tense":null,"voice":null,"mood":null,"person":null},"id":"Ps.31.3.8","verseId":"Ps.31.3"},{"position":9,"surface":"κράζειν","lemma":"κράζειν","strongs":"2896","morph":{"partOfSpeech":"Verb","casus":null,"number":null,"gender":null,"tense":"Present","voice":"Active","mood":"Infinitive","person":null},"id":"Ps.31.3.9","verseId":"Ps.31.3"},{"position":10,"surface":"με","lemma":"με","strongs":"3165","morph":{"partOfSpeech":"RP","casus":"Accusative","number":"Singular","tense":null,"voice":null,"mood":null,"person":null},"id":"Ps.31.3.10","verseId":"Ps.31.3"},{"position":11,"surface":"ὅλην","lemma":"ὅλην","strongs":"3650","morph":{"partOfSpeech":"Adjective","casus":"Accusative","number":"Singular","gender":"Feminine","tense":null,"voice":null,"mood":null,"person":null},"id":"Ps.31.3.11","verseId":"Ps.31.3"},{"position":12,"surface":"τὴν","lemma":"τὴν","strongs":"3588","morph":{"partOfSpeech":"Article","casus":"Accusative","number":"Singular","gender":"Feminine","tense":null,"voice":null,"mood":null,"person":null},"id":"Ps.31.3.12","verseId":"Ps.31.3"},{"position":13,"surface":"ἡμέραν","lemma":"ἡμέραν","strongs":"2250","morph":{"partOfSpeech":"Noun","casus":"Accusative","number":"Singular","gender":"Feminine","tense":null,"voice":null,"mood":null,"person":null},"id":"Ps.31.3.13","verseId":"Ps.31.3"}]},{"id":"Ps.31.4","bookId":"Ps","chapter":31,"verse":4,"reference":"Psalms 31:4","text":"ὅτι ἡμέρας καὶ νυκτὸς ἐβαρύνθη ἐπ᾿ ἐμὲ ἡ χείρ σου ἐστράφην εἰς ταλαιπωρίαν ἐν τῷ ἐμπαγῆναι ἄκανθαν διάψαλμα","words":[{"position":1,"surface":"ὅτι","lemma":"ὅτι","strongs":"3754","morph":{"partOfSpeech":"Conjunction","casus":null,"number":null,"gender":null,"tense":null,"voice":null,"mood":null,"person":null},"id":"Ps.31.4.1","verseId":"Ps.31.4"},{"position":2,"surface":"ἡμέρας","lemma":"ἡμέρας","strongs":"2250","morph":{"partOfSpeech":"Noun","casus":"Genitive","number":"Singular","gender":"Feminine","tense":null,"voice":null,"mood":null,"person":null},"id":"Ps.31.4.2","verseId":"Ps.31.4"},{"position":3,"surface":"καὶ","lemma":"καὶ","strongs":"2532","morph":{"partOfSpeech":"Conjunction","casus":null,"number":null,"gender":null,"tense":null,"voice":null,"mood":null,"person":null},"id":"Ps.31.4.3","verseId":"Ps.31.4"},{"position":4,"surface":"νυκτὸς","lemma":"νυκτὸς","strongs":"3571","morph":{"partOfSpeech":"Noun","casus":"Genitive","number":"Singular","gender":"Feminine","tense":null,"voice":null,"mood":null,"person":null},"id":"Ps.31.4.4","verseId":"Ps.31.4"},{"position":5,"surface":"ἐβαρύνθη","lemma":"ἐβαρύνθη","strongs":"925","morph":{"partOfSpeech":"Verb","casus":null,"number":"Singular","gender":null,"tense":"Aorist","voice":"Passive","mood":"Indicative","person":"3"},"id":"Ps.31.4.5","verseId":"Ps.31.4"},{"position":6,"surface":"ἐπ᾿","lemma":"ἐπ᾿","strongs":"1909","morph":{"partOfSpeech":"Preposition","casus":null,"number":null,"gender":null,"tense":null,"voice":null,"mood":null,"person":null},"id":"Ps.31.4.6","verseId":"Ps.31.4"},{"position":7,"surface":"ἐμὲ","lemma":"ἐμὲ","strongs":"1691","morph":{"partOfSpeech":"RP","casus":"Accusative","number":"Singular","tense":null,"voice":null,"mood":null,"person":null},"id":"Ps.31.4.7","verseId":"Ps.31.4"},{"position":8,"surface":"ἡ","lemma":"ἡ","strongs":"3588","morph":{"partOfSpeech":"Article","casus":"Nominative","number":"Singular","gender":"Feminine","tense":null,"voice":null,"mood":null,"person":null},"id":"Ps.31.4.8","verseId":"Ps.31.4"},{"position":9,"surface":"χείρ","lemma":"χείρ","strongs":"5495","morph":{"partOfSpeech":"Noun","casus":"Nominative","number":"Singular","gender":"Feminine","tense":null,"voice":null,"mood":null,"person":null},"id":"Ps.31.4.9","verseId":"Ps.31.4"},{"position":10,"surface":"σου","lemma":"σου","strongs":"4675","morph":{"partOfSpeech":"RP","casus":"Genitive","number":"Singular","tense":null,"voice":null,"mood":null,"person":null},"id":"Ps.31.4.10","verseId":"Ps.31.4"},{"position":11,"surface":"ἐστράφην","lemma":"ἐστράφην","strongs":"4762","morph":{"partOfSpeech":"Verb","casus":null,"number":"Singular","gender":null,"tense":"Aorist","voice":"Passive","mood":"Indicative","person":"1"},"id":"Ps.31.4.11","verseId":"Ps.31.4"},{"position":12,"surface":"εἰς","lemma":"εἰς","strongs":"1519","morph":{"partOfSpeech":"Preposition","casus":null,"number":null,"gender":null,"tense":null,"voice":null,"mood":null,"person":null},"id":"Ps.31.4.12","verseId":"Ps.31.4"},{"position":13,"surface":"ταλαιπωρίαν","lemma":"ταλαιπωρίαν","strongs":"5004","morph":{"partOfSpeech":"Noun","casus":"Accusative","number":"Singular","gender":"Feminine","tense":null,"voice":null,"mood":null,"person":null},"id":"Ps.31.4.13","verseId":"Ps.31.4"},{"position":14,"surface":"ἐν","lemma":"ἐν","strongs":"1722","morph":{"partOfSpeech":"Preposition","casus":null,"number":null,"gender":null,"tense":null,"voice":null,"mood":null,"person":null},"id":"Ps.31.4.14","verseId":"Ps.31.4"},{"position":15,"surface":"τῷ","lemma":"τῷ","strongs":"3588","morph":{"partOfSpeech":"Article","casus":"Dative","number":"Singular","gender":"Neuter","tense":null,"voice":null,"mood":null,"person":null},"id":"Ps.31.4.15","verseId":"Ps.31.4"},{"position":16,"surface":"ἐμπαγῆναι","lemma":"ἐμπαγῆναι","strongs":"","morph":{"partOfSpeech":"Verb","casus":null,"number":null,"gender":null,"tense":"Aorist","voice":"Passive","mood":"Infinitive","person":null},"id":"Ps.31.4.16","verseId":"Ps.31.4"},{"position":17,"surface":"ἄκανθαν","lemma":"ἄκανθαν","strongs":"173","morph":{"partOfSpeech":"Noun","casus":"Accusative","number":"Singular","gender":"Feminine","tense":null,"voice":null,"mood":null,"person":null},"id":"Ps.31.4.17","verseId":"Ps.31.4"},{"position":18,"surface":"διάψαλμα","lemma":"διάψαλμα","strongs":"","morph":{"partOfSpeech":"Noun","casus":"Nominative","number":"Singular","gender":"Neuter","tense":null,"voice":null,"mood":null,"person":null},"id":"Ps.31.4.18","verseId":"Ps.31.4"}]},{"id":"Ps.31.5","bookId":"Ps","chapter":31,"verse":5,"reference":"Psalms 31:5","text":"τὴν ἁμαρτίαν μου ἐγνώρισα καὶ τὴν ἀνομίαν μου οὐκ ἐκάλυψα εἶπα ἐξαγορεύσω κατ᾿ ἐμοῦ τὴν ἀνομίαν μου τῷ κυρίῳ καὶ σὺ ἀφῆκας τὴν ἀσέβειαν τῆς ἁμαρτίας μου διάψαλμα","words":[{"position":1,"surface":"τὴν","lemma":"τὴν","strongs":"3588","morph":{"partOfSpeech":"Article","casus":"Accusative","number":"Singular","gender":"Feminine","tense":null,"voice":null,"mood":null,"person":null},"id":"Ps.31.5.1","verseId":"Ps.31.5"},{"position":2,"surface":"ἁμαρτίαν","lemma":"ἁμαρτίαν","strongs":"266","morph":{"partOfSpeech":"Noun","casus":"Accusative","number":"Singular","gender":"Feminine","tense":null,"voice":null,"mood":null,"person":null},"id":"Ps.31.5.2","verseId":"Ps.31.5"},{"position":3,"surface":"μου","lemma":"μου","strongs":"3450","morph":{"partOfSpeech":"RP","casus":"Genitive","number":"Singular","tense":null,"voice":null,"mood":null,"person":null},"id":"Ps.31.5.3","verseId":"Ps.31.5"},{"position":4,"surface":"ἐγνώρισα","lemma":"ἐγνώρισα","strongs":"1107","morph":{"partOfSpeech":"Verb","casus":null,"number":"Singular","gender":null,"tense":"Aorist","voice":"Active","mood":"Indicative","person":"1"},"id":"Ps.31.5.4","verseId":"Ps.31.5"},{"position":5,"surface":"καὶ","lemma":"καὶ","strongs":"2532","morph":{"partOfSpeech":"Conjunction","casus":null,"number":null,"gender":null,"tense":null,"voice":null,"mood":null,"person":null},"id":"Ps.31.5.5","verseId":"Ps.31.5"},{"position":6,"surface":"τὴν","lemma":"τὴν","strongs":"3588","morph":{"partOfSpeech":"Article","casus":"Accusative","number":"Singular","gender":"Feminine","tense":null,"voice":null,"mood":null,"person":null},"id":"Ps.31.5.6","verseId":"Ps.31.5"},{"position":7,"surface":"ἀνομίαν","lemma":"ἀνομίαν","strongs":"458","morph":{"partOfSpeech":"Noun","casus":"Accusative","number":"Singular","gender":"Feminine","tense":null,"voice":null,"mood":null,"person":null},"id":"Ps.31.5.7","verseId":"Ps.31.5"},{"position":8,"surface":"μου","lemma":"μου","strongs":"3450","morph":{"partOfSpeech":"RP","casus":"Genitive","number":"Singular","tense":null,"voice":null,"mood":null,"person":null},"id":"Ps.31.5.8","verseId":"Ps.31.5"},{"position":9,"surface":"οὐκ","lemma":"οὐκ","strongs":"3756","morph":{"partOfSpeech":"Adverb","casus":null,"number":null,"gender":null,"tense":null,"voice":null,"mood":null,"person":null},"id":"Ps.31.5.9","verseId":"Ps.31.5"},{"position":10,"surface":"ἐκάλυψα","lemma":"ἐκάλυψα","strongs":"2572","morph":{"partOfSpeech":"Verb","casus":null,"number":"Singular","gender":null,"tense":"Aorist","voice":"Active","mood":"Indicative","person":"1"},"id":"Ps.31.5.10","verseId":"Ps.31.5"},{"position":11,"surface":"εἶπα","lemma":"εἶπα","strongs":"2036","morph":{"partOfSpeech":"Verb","casus":null,"number":"Singular","gender":null,"tense":"Aorist","voice":"Active","mood":"Indicative","person":"1"},"id":"Ps.31.5.11","verseId":"Ps.31.5"},{"position":12,"surface":"ἐξαγορεύσω","lemma":"ἐξαγορεύσω","strongs":"","morph":{"partOfSpeech":"Verb","casus":null,"number":"Singular","gender":null,"tense":"Future","voice":"Active","mood":"Indicative","person":"1"},"id":"Ps.31.5.12","verseId":"Ps.31.5"},{"position":13,"surface":"κατ᾿","lemma":"κατ᾿","strongs":"2596","morph":{"partOfSpeech":"Preposition","casus":null,"number":null,"gender":null,"tense":null,"voice":null,"mood":null,"person":null},"id":"Ps.31.5.13","verseId":"Ps.31.5"},{"position":14,"surface":"ἐμοῦ","lemma":"ἐμοῦ","strongs":"1700","morph":{"partOfSpeech":"RP","casus":"Genitive","number":"Singular","tense":null,"voice":null,"mood":null,"person":null},"id":"Ps.31.5.14","verseId":"Ps.31.5"},{"position":15,"surface":"τὴν","lemma":"τὴν","strongs":"3588","morph":{"partOfSpeech":"Article","casus":"Accusative","number":"Singular","gender":"Feminine","tense":null,"voice":null,"mood":null,"person":null},"id":"Ps.31.5.15","verseId":"Ps.31.5"},{"position":16,"surface":"ἀνομίαν","lemma":"ἀνομίαν","strongs":"458","morph":{"partOfSpeech":"Noun","casus":"Accusative","number":"Singular","gender":"Feminine","tense":null,"voice":null,"mood":null,"person":null},"id":"Ps.31.5.16","verseId":"Ps.31.5"},{"position":17,"surface":"μου","lemma":"μου","strongs":"3450","morph":{"partOfSpeech":"RP","casus":"Genitive","number":"Singular","tense":null,"voice":null,"mood":null,"person":null},"id":"Ps.31.5.17","verseId":"Ps.31.5"},{"position":18,"surface":"τῷ","lemma":"τῷ","strongs":"3588","morph":{"partOfSpeech":"Article","casus":"Dative","number":"Singular","gender":"Masculine","tense":null,"voice":null,"mood":null,"person":null},"id":"Ps.31.5.18","verseId":"Ps.31.5"},{"position":19,"surface":"κυρίῳ","lemma":"κυρίῳ","strongs":"2962","morph":{"partOfSpeech":"Noun","casus":"Dative","number":"Singular","gender":"Masculine","tense":null,"voice":null,"mood":null,"person":null},"id":"Ps.31.5.19","verseId":"Ps.31.5"},{"position":20,"surface":"καὶ","lemma":"καὶ","strongs":"2532","morph":{"partOfSpeech":"Conjunction","casus":null,"number":null,"gender":null,"tense":null,"voice":null,"mood":null,"person":null},"id":"Ps.31.5.20","verseId":"Ps.31.5"},{"position":21,"surface":"σὺ","lemma":"σὺ","strongs":"4771","morph":{"partOfSpeech":"RP","casus":"Nominative","number":"Singular","tense":null,"voice":null,"mood":null,"person":null},"id":"Ps.31.5.21","verseId":"Ps.31.5"},{"position":22,"surface":"ἀφῆκας","lemma":"ἀφῆκας","strongs":"863","morph":{"partOfSpeech":"Verb","casus":null,"number":"Singular","gender":null,"tense":"Aorist","voice":"Active","mood":"Indicative","person":"2"},"id":"Ps.31.5.22","verseId":"Ps.31.5"},{"position":23,"surface":"τὴν","lemma":"τὴν","strongs":"3588","morph":{"partOfSpeech":"Article","casus":"Accusative","number":"Singular","gender":"Feminine","tense":null,"voice":null,"mood":null,"person":null},"id":"Ps.31.5.23","verseId":"Ps.31.5"},{"position":24,"surface":"ἀσέβειαν","lemma":"ἀσέβειαν","strongs":"763","morph":{"partOfSpeech":"Noun","casus":"Accusative","number":"Singular","gender":"Feminine","tense":null,"voice":null,"mood":null,"person":null},"id":"Ps.31.5.24","verseId":"Ps.31.5"},{"position":25,"surface":"τῆς","lemma":"τῆς","strongs":"3588","morph":{"partOfSpeech":"Article","casus":"Genitive","number":"Singular","gender":"Feminine","tense":null,"voice":null,"mood":null,"person":null},"id":"Ps.31.5.25","verseId":"Ps.31.5"},{"position":26,"surface":"ἁμαρτίας","lemma":"ἁμαρτίας","strongs":"266","morph":{"partOfSpeech":"Noun","casus":"Genitive","number":"Singular","gender":"Feminine","tense":null,"voice":null,"mood":null,"person":null},"id":"Ps.31.5.26","verseId":"Ps.31.5"},{"position":27,"surface":"μου","lemma":"μου","strongs":"3450","morph":{"partOfSpeech":"RP","casus":"Genitive","number":"Singular","tense":null,"voice":null,"mood":null,"person":null},"id":"Ps.31.5.27","verseId":"Ps.31.5"},{"position":28,"surface":"διάψαλμα","lemma":"διάψαλμα","strongs":"","morph":{"partOfSpeech":"Noun","casus":"Nominative","number":"Singular","gender":"Neuter","tense":null,"voice":null,"mood":null,"person":null},"id":"Ps.31.5.28","verseId":"Ps.31.5"}]},{"id":"Ps.31.6","bookId":"Ps","chapter":31,"verse":6,"reference":"Psalms 31:6","text":"ὑπὲρ ταύτης προσεύξεται πᾶς ὅσιος πρὸς σὲ ἐν καιρῷ εὐθέτῳ πλὴν ἐν κατακλυσμῷ ὑδάτων πολλῶν πρὸς αὐτὸν οὐκ ἐγγιοῦσιν","words":[{"position":1,"surface":"ὑπὲρ","lemma":"ὑπὲρ","strongs":"5228","morph":{"partOfSpeech":"Preposition","casus":null,"number":null,"gender":null,"tense":null,"voice":null,"mood":null,"person":null},"id":"Ps.31.6.1","verseId":"Ps.31.6"},{"position":2,"surface":"ταύτης","lemma":"ταύτης","strongs":"3778","morph":{"partOfSpeech":"Demonstrative","casus":"Genitive","number":"Singular","gender":"Feminine","tense":null,"voice":null,"mood":null,"person":null},"id":"Ps.31.6.2","verseId":"Ps.31.6"},{"position":3,"surface":"προσεύξεται","lemma":"προσεύξεται","strongs":"4336","morph":{"partOfSpeech":"Verb","casus":null,"number":"Singular","gender":null,"tense":"Future","voice":"Middle","mood":"Indicative","person":"3"},"id":"Ps.31.6.3","verseId":"Ps.31.6"},{"position":4,"surface":"πᾶς","lemma":"πᾶς","strongs":"3956","morph":{"partOfSpeech":"Adjective","casus":"Nominative","number":"Singular","gender":"Masculine","tense":null,"voice":null,"mood":null,"person":null},"id":"Ps.31.6.4","verseId":"Ps.31.6"},{"position":5,"surface":"ὅσιος","lemma":"ὅσιος","strongs":"3741","morph":{"partOfSpeech":"Adjective","casus":"Nominative","number":"Singular","gender":"Masculine","tense":null,"voice":null,"mood":null,"person":null},"id":"Ps.31.6.5","verseId":"Ps.31.6"},{"position":6,"surface":"πρὸς","lemma":"πρὸς","strongs":"4314","morph":{"partOfSpeech":"Preposition","casus":null,"number":null,"gender":null,"tense":null,"voice":null,"mood":null,"person":null},"id":"Ps.31.6.6","verseId":"Ps.31.6"},{"position":7,"surface":"σὲ","lemma":"σὲ","strongs":"4571","morph":{"partOfSpeech":"RP","casus":"Accusative","number":"Singular","tense":null,"voice":null,"mood":null,"person":null},"id":"Ps.31.6.7","verseId":"Ps.31.6"},{"position":8,"surface":"ἐν","lemma":"ἐν","strongs":"1722","morph":{"partOfSpeech":"Preposition","casus":null,"number":null,"gender":null,"tense":null,"voice":null,"mood":null,"person":null},"id":"Ps.31.6.8","verseId":"Ps.31.6"},{"position":9,"surface":"καιρῷ","lemma":"καιρῷ","strongs":"2540","morph":{"partOfSpeech":"Noun","casus":"Dative","number":"Singular","gender":"Masculine","tense":null,"voice":null,"mood":null,"person":null},"id":"Ps.31.6.9","verseId":"Ps.31.6"},{"position":10,"surface":"εὐθέτῳ","lemma":"εὐθέτῳ","strongs":"2111","morph":{"partOfSpeech":"Adjective","casus":"Dative","number":"Singular","gender":"Masculine","tense":null,"voice":null,"mood":null,"person":null},"id":"Ps.31.6.10","verseId":"Ps.31.6"},{"position":11,"surface":"πλὴν","lemma":"πλὴν","strongs":"4133","morph":{"partOfSpeech":"Adverb","casus":null,"number":null,"gender":null,"tense":null,"voice":null,"mood":null,"person":null},"id":"Ps.31.6.11","verseId":"Ps.31.6"},{"position":12,"surface":"ἐν","lemma":"ἐν","strongs":"1722","morph":{"partOfSpeech":"Preposition","casus":null,"number":null,"gender":null,"tense":null,"voice":null,"mood":null,"person":null},"id":"Ps.31.6.12","verseId":"Ps.31.6"},{"position":13,"surface":"κατακλυσμῷ","lemma":"κατακλυσμῷ","strongs":"2627","morph":{"partOfSpeech":"Noun","casus":"Dative","number":"Singular","gender":"Masculine","tense":null,"voice":null,"mood":null,"person":null},"id":"Ps.31.6.13","verseId":"Ps.31.6"},{"position":14,"surface":"ὑδάτων","lemma":"ὑδάτων","strongs":"5204","morph":{"partOfSpeech":"Noun","casus":"Genitive","number":"Plural","gender":"Neuter","tense":null,"voice":null,"mood":null,"person":null},"id":"Ps.31.6.14","verseId":"Ps.31.6"},{"position":15,"surface":"πολλῶν","lemma":"πολλῶν","strongs":"4183","morph":{"partOfSpeech":"Adjective","casus":"Genitive","number":"Plural","gender":"Neuter","tense":null,"voice":null,"mood":null,"person":null},"id":"Ps.31.6.15","verseId":"Ps.31.6"},{"position":16,"surface":"πρὸς","lemma":"πρὸς","strongs":"4314","morph":{"partOfSpeech":"Preposition","casus":null,"number":null,"gender":null,"tense":null,"voice":null,"mood":null,"person":null},"id":"Ps.31.6.16","verseId":"Ps.31.6"},{"position":17,"surface":"αὐτὸν","lemma":"αὐτὸν","strongs":"846","morph":{"partOfSpeech":"Demonstrative","casus":"Accusative","number":"Singular","gender":"Masculine","tense":null,"voice":null,"mood":null,"person":null},"id":"Ps.31.6.17","verseId":"Ps.31.6"},{"position":18,"surface":"οὐκ","lemma":"οὐκ","strongs":"3756","morph":{"partOfSpeech":"Adverb","casus":null,"number":null,"gender":null,"tense":null,"voice":null,"mood":null,"person":null},"id":"Ps.31.6.18","verseId":"Ps.31.6"},{"position":19,"surface":"ἐγγιοῦσιν","lemma":"ἐγγιοῦσιν","strongs":"1448","morph":{"partOfSpeech":"Verb","casus":null,"number":"Plural","gender":null,"tense":"Future","voice":"Active","mood":"Indicative","person":"3"},"id":"Ps.31.6.19","verseId":"Ps.31.6"}]},{"id":"Ps.31.7","bookId":"Ps","chapter":31,"verse":7,"reference":"Psalms 31:7","text":"σύ μου εἶ καταφυγὴ ἀπὸ θλίψεως τῆς περιεχούσης με τὸ ἀγαλλίαμά μου λύτρωσαί με ἀπὸ τῶν κυκλωσάντων με διάψαλμα","words":[{"position":1,"surface":"σύ","lemma":"σύ","strongs":"4771","morph":{"partOfSpeech":"RP","casus":"Nominative","number":"Singular","tense":null,"voice":null,"mood":null,"person":null},"id":"Ps.31.7.1","verseId":"Ps.31.7"},{"position":2,"surface":"μου","lemma":"μου","strongs":"3450","morph":{"partOfSpeech":"RP","casus":"Genitive","number":"Singular","tense":null,"voice":null,"mood":null,"person":null},"id":"Ps.31.7.2","verseId":"Ps.31.7"},{"position":3,"surface":"εἶ","lemma":"εἶ","strongs":"1510","morph":{"partOfSpeech":"Verb","casus":null,"number":"Singular","gender":null,"tense":"Present","voice":"Active","mood":"Indicative","person":"2"},"id":"Ps.31.7.3","verseId":"Ps.31.7"},{"position":4,"surface":"καταφυγὴ","lemma":"καταφυγὴ","strongs":"","morph":{"partOfSpeech":"Noun","casus":"Nominative","number":"Singular","gender":"Feminine","tense":null,"voice":null,"mood":null,"person":null},"id":"Ps.31.7.4","verseId":"Ps.31.7"},{"position":5,"surface":"ἀπὸ","lemma":"ἀπὸ","strongs":"575","morph":{"partOfSpeech":"Preposition","casus":null,"number":null,"gender":null,"tense":null,"voice":null,"mood":null,"person":null},"id":"Ps.31.7.5","verseId":"Ps.31.7"},{"position":6,"surface":"θλίψεως","lemma":"θλίψεως","strongs":"2347","morph":{"partOfSpeech":"Noun","casus":"Genitive","number":"Singular","gender":"Feminine","tense":null,"voice":null,"mood":null,"person":null},"id":"Ps.31.7.6","verseId":"Ps.31.7"},{"position":7,"surface":"τῆς","lemma":"τῆς","strongs":"3588","morph":{"partOfSpeech":"Article","casus":"Genitive","number":"Singular","gender":"Feminine","tense":null,"voice":null,"mood":null,"person":null},"id":"Ps.31.7.7","verseId":"Ps.31.7"},{"position":8,"surface":"περιεχούσης","lemma":"περιεχούσης","strongs":"4023","morph":{"partOfSpeech":"Verb","casus":"Genitive","number":"Singular","gender":"Feminine","tense":"Present","voice":"Active","mood":"Participle","person":null},"id":"Ps.31.7.8","verseId":"Ps.31.7"},{"position":9,"surface":"με","lemma":"με","strongs":"3165","morph":{"partOfSpeech":"RP","casus":"Accusative","number":"Singular","tense":null,"voice":null,"mood":null,"person":null},"id":"Ps.31.7.9","verseId":"Ps.31.7"},{"position":10,"surface":"τὸ","lemma":"τὸ","strongs":"3588","morph":{"partOfSpeech":"Article","casus":"Accusative","number":"Singular","gender":"Neuter","tense":null,"voice":null,"mood":null,"person":null},"id":"Ps.31.7.10","verseId":"Ps.31.7"},{"position":11,"surface":"ἀγαλλίαμά","lemma":"ἀγαλλίαμά","strongs":"","morph":{"partOfSpeech":"Noun","casus":"Accusative","number":"Singular","gender":"Neuter","tense":null,"voice":null,"mood":null,"person":null},"id":"Ps.31.7.11","verseId":"Ps.31.7"},{"position":12,"surface":"μου","lemma":"μου","strongs":"3450","morph":{"partOfSpeech":"RP","casus":"Genitive","number":"Singular","tense":null,"voice":null,"mood":null,"person":null},"id":"Ps.31.7.12","verseId":"Ps.31.7"},{"position":13,"surface":"λύτρωσαί","lemma":"λύτρωσαί","strongs":"3084","morph":{"partOfSpeech":"Verb","casus":null,"number":null,"gender":null,"tense":"Aorist","voice":"Active","mood":"Infinitive","person":null},"id":"Ps.31.7.13","verseId":"Ps.31.7"},{"position":14,"surface":"με","lemma":"με","strongs":"3165","morph":{"partOfSpeech":"RP","casus":"Accusative","number":"Singular","tense":null,"voice":null,"mood":null,"person":null},"id":"Ps.31.7.14","verseId":"Ps.31.7"},{"position":15,"surface":"ἀπὸ","lemma":"ἀπὸ","strongs":"575","morph":{"partOfSpeech":"Preposition","casus":null,"number":null,"gender":null,"tense":null,"voice":null,"mood":null,"person":null},"id":"Ps.31.7.15","verseId":"Ps.31.7"},{"position":16,"surface":"τῶν","lemma":"τῶν","strongs":"3588","morph":{"partOfSpeech":"Article","casus":"Genitive","number":"Plural","gender":"Masculine","tense":null,"voice":null,"mood":null,"person":null},"id":"Ps.31.7.16","verseId":"Ps.31.7"},{"position":17,"surface":"κυκλωσάντων","lemma":"κυκλωσάντων","strongs":"2944","morph":{"partOfSpeech":"Verb","casus":"Genitive","number":"Plural","gender":"Masculine","tense":"Aorist","voice":"Active","mood":"Participle","person":null},"id":"Ps.31.7.17","verseId":"Ps.31.7"},{"position":18,"surface":"με","lemma":"με","strongs":"3165","morph":{"partOfSpeech":"RP","casus":"Accusative","number":"Singular","tense":null,"voice":null,"mood":null,"person":null},"id":"Ps.31.7.18","verseId":"Ps.31.7"},{"position":19,"surface":"διάψαλμα","lemma":"διάψαλμα","strongs":"","morph":{"partOfSpeech":"Noun","casus":"Nominative","number":"Singular","gender":"Neuter","tense":null,"voice":null,"mood":null,"person":null},"id":"Ps.31.7.19","verseId":"Ps.31.7"}]},{"id":"Ps.31.8","bookId":"Ps","chapter":31,"verse":8,"reference":"Psalms 31:8","text":"συνετιῶ σε καὶ συμβιβῶ σε ἐν ὁδῷ ταύτῃ ᾗ πορεύσῃ ἐπιστηριῶ ἐπὶ σὲ τοὺς ὀφθαλμούς μου","words":[{"position":1,"surface":"συνετιῶ","lemma":"συνετιῶ","strongs":"","morph":{"partOfSpeech":"Verb","casus":null,"number":"Singular","gender":null,"tense":"Future","voice":"Active","mood":"Indicative","person":"1"},"id":"Ps.31.8.1","verseId":"Ps.31.8"},{"position":2,"surface":"σε","lemma":"σε","strongs":"4571","morph":{"partOfSpeech":"RP","casus":"Accusative","number":"Singular","tense":null,"voice":null,"mood":null,"person":null},"id":"Ps.31.8.2","verseId":"Ps.31.8"},{"position":3,"surface":"καὶ","lemma":"καὶ","strongs":"2532","morph":{"partOfSpeech":"Conjunction","casus":null,"number":null,"gender":null,"tense":null,"voice":null,"mood":null,"person":null},"id":"Ps.31.8.3","verseId":"Ps.31.8"},{"position":4,"surface":"συμβιβῶ","lemma":"συμβιβῶ","strongs":"4822","morph":{"partOfSpeech":"Verb","casus":null,"number":"Singular","gender":null,"tense":"Future","voice":"Active","mood":"Indicative","person":"1"},"id":"Ps.31.8.4","verseId":"Ps.31.8"},{"position":5,"surface":"σε","lemma":"σε","strongs":"4571","morph":{"partOfSpeech":"RP","casus":"Accusative","number":"Singular","tense":null,"voice":null,"mood":null,"person":null},"id":"Ps.31.8.5","verseId":"Ps.31.8"},{"position":6,"surface":"ἐν","lemma":"ἐν","strongs":"1722","morph":{"partOfSpeech":"Preposition","casus":null,"number":null,"gender":null,"tense":null,"voice":null,"mood":null,"person":null},"id":"Ps.31.8.6","verseId":"Ps.31.8"},{"position":7,"surface":"ὁδῷ","lemma":"ὁδῷ","strongs":"3598","morph":{"partOfSpeech":"Noun","casus":"Dative","number":"Singular","gender":"Feminine","tense":null,"voice":null,"mood":null,"person":null},"id":"Ps.31.8.7","verseId":"Ps.31.8"},{"position":8,"surface":"ταύτῃ","lemma":"ταύτῃ","strongs":"3778","morph":{"partOfSpeech":"Demonstrative","casus":"Dative","number":"Singular","gender":"Feminine","tense":null,"voice":null,"mood":null,"person":null},"id":"Ps.31.8.8","verseId":"Ps.31.8"},{"position":9,"surface":"ᾗ","lemma":"ᾗ","strongs":"3739","morph":{"partOfSpeech":"Relative Pronoun","casus":"Dative","number":"Singular","gender":"Feminine","tense":null,"voice":null,"mood":null,"person":null},"id":"Ps.31.8.9","verseId":"Ps.31.8"},{"position":10,"surface":"πορεύσῃ","lemma":"πορεύσῃ","strongs":"4198","morph":{"partOfSpeech":"Verb","casus":null,"number":"Singular","gender":null,"tense":"Aorist","voice":"Active","mood":"Subjunctive","person":"3"},"id":"Ps.31.8.10","verseId":"Ps.31.8"},{"position":11,"surface":"ἐπιστηριῶ","lemma":"ἐπιστηριῶ","strongs":"1991","morph":{"partOfSpeech":"Verb","casus":null,"number":"Singular","gender":null,"tense":"Future","voice":"Active","mood":"Indicative","person":"1"},"id":"Ps.31.8.11","verseId":"Ps.31.8"},{"position":12,"surface":"ἐπὶ","lemma":"ἐπὶ","strongs":"1909","morph":{"partOfSpeech":"Preposition","casus":null,"number":null,"gender":null,"tense":null,"voice":null,"mood":null,"person":null},"id":"Ps.31.8.12","verseId":"Ps.31.8"},{"position":13,"surface":"σὲ","lemma":"σὲ","strongs":"4571","morph":{"partOfSpeech":"RP","casus":"Accusative","number":"Singular","tense":null,"voice":null,"mood":null,"person":null},"id":"Ps.31.8.13","verseId":"Ps.31.8"},{"position":14,"surface":"τοὺς","lemma":"τοὺς","strongs":"3588","morph":{"partOfSpeech":"Article","casus":"Accusative","number":"Plural","gender":"Masculine","tense":null,"voice":null,"mood":null,"person":null},"id":"Ps.31.8.14","verseId":"Ps.31.8"},{"position":15,"surface":"ὀφθαλμούς","lemma":"ὀφθαλμούς","strongs":"3788","morph":{"partOfSpeech":"Noun","casus":"Accusative","number":"Plural","gender":"Masculine","tense":null,"voice":null,"mood":null,"person":null},"id":"Ps.31.8.15","verseId":"Ps.31.8"},{"position":16,"surface":"μου","lemma":"μου","strongs":"3450","morph":{"partOfSpeech":"RP","casus":"Genitive","number":"Singular","tense":null,"voice":null,"mood":null,"person":null},"id":"Ps.31.8.16","verseId":"Ps.31.8"}]},{"id":"Ps.31.9","bookId":"Ps","chapter":31,"verse":9,"reference":"Psalms 31:9","text":"μὴ γίνεσθε ὡς ἵππος καὶ ἡμίονος οἷς οὐκ ἔστιν σύνεσις ἐν χαλινῷ καὶ κημῷ τὰς σιαγόνας αὐτῶν ἄγξαι τῶν μὴ ἐγγιζόντων πρὸς σέ","words":[{"position":1,"surface":"μὴ","lemma":"μὴ","strongs":"3361","morph":{"partOfSpeech":"Adverb","casus":null,"number":null,"gender":null,"tense":null,"voice":null,"mood":null,"person":null},"id":"Ps.31.9.1","verseId":"Ps.31.9"},{"position":2,"surface":"γίνεσθε","lemma":"γίνεσθε","strongs":"1096","morph":{"partOfSpeech":"Verb","casus":null,"number":"Plural","gender":null,"tense":"Present","voice":"Middle","mood":"Imperative","person":"2"},"id":"Ps.31.9.2","verseId":"Ps.31.9"},{"position":3,"surface":"ὡς","lemma":"ὡς","strongs":"5613","morph":{"partOfSpeech":"Conjunction","casus":null,"number":null,"gender":null,"tense":null,"voice":null,"mood":null,"person":null},"id":"Ps.31.9.3","verseId":"Ps.31.9"},{"position":4,"surface":"ἵππος","lemma":"ἵππος","strongs":"2462","morph":{"partOfSpeech":"Noun","casus":"Nominative","number":"Singular","gender":"Masculine","tense":null,"voice":null,"mood":null,"person":null},"id":"Ps.31.9.4","verseId":"Ps.31.9"},{"position":5,"surface":"καὶ","lemma":"καὶ","strongs":"2532","morph":{"partOfSpeech":"Conjunction","casus":null,"number":null,"gender":null,"tense":null,"voice":null,"mood":null,"person":null},"id":"Ps.31.9.5","verseId":"Ps.31.9"},{"position":6,"surface":"ἡμίονος","lemma":"ἡμίονος","strongs":"","morph":{"partOfSpeech":"Noun","casus":"Nominative","number":"Singular","gender":"Masculine","tense":null,"voice":null,"mood":null,"person":null},"id":"Ps.31.9.6","verseId":"Ps.31.9"},{"position":7,"surface":"οἷς","lemma":"οἷς","strongs":"3739","morph":{"partOfSpeech":"Relative Pronoun","casus":"Dative","number":"Plural","gender":"Masculine","tense":null,"voice":null,"mood":null,"person":null},"id":"Ps.31.9.7","verseId":"Ps.31.9"},{"position":8,"surface":"οὐκ","lemma":"οὐκ","strongs":"3756","morph":{"partOfSpeech":"Adverb","casus":null,"number":null,"gender":null,"tense":null,"voice":null,"mood":null,"person":null},"id":"Ps.31.9.8","verseId":"Ps.31.9"},{"position":9,"surface":"ἔστιν","lemma":"ἔστιν","strongs":"1510","morph":{"partOfSpeech":"Verb","casus":null,"number":"Singular","gender":null,"tense":"Present","voice":"Active","mood":"Indicative","person":"3"},"id":"Ps.31.9.9","verseId":"Ps.31.9"},{"position":10,"surface":"σύνεσις","lemma":"σύνεσις","strongs":"4907","morph":{"partOfSpeech":"Noun","casus":"Nominative","number":"Singular","gender":"Feminine","tense":null,"voice":null,"mood":null,"person":null},"id":"Ps.31.9.10","verseId":"Ps.31.9"},{"position":11,"surface":"ἐν","lemma":"ἐν","strongs":"1722","morph":{"partOfSpeech":"Preposition","casus":null,"number":null,"gender":null,"tense":null,"voice":null,"mood":null,"person":null},"id":"Ps.31.9.11","verseId":"Ps.31.9"},{"position":12,"surface":"χαλινῷ","lemma":"χαλινῷ","strongs":"5469","morph":{"partOfSpeech":"Noun","casus":"Dative","number":"Singular","gender":"Masculine","tense":null,"voice":null,"mood":null,"person":null},"id":"Ps.31.9.12","verseId":"Ps.31.9"},{"position":13,"surface":"καὶ","lemma":"καὶ","strongs":"2532","morph":{"partOfSpeech":"Conjunction","casus":null,"number":null,"gender":null,"tense":null,"voice":null,"mood":null,"person":null},"id":"Ps.31.9.13","verseId":"Ps.31.9"},{"position":14,"surface":"κημῷ","lemma":"κημῷ","strongs":"","morph":{"partOfSpeech":"Noun","casus":"Dative","number":"Singular","gender":"Masculine","tense":null,"voice":null,"mood":null,"person":null},"id":"Ps.31.9.14","verseId":"Ps.31.9"},{"position":15,"surface":"τὰς","lemma":"τὰς","strongs":"3588","morph":{"partOfSpeech":"Article","casus":"Accusative","number":"Plural","gender":"Feminine","tense":null,"voice":null,"mood":null,"person":null},"id":"Ps.31.9.15","verseId":"Ps.31.9"},{"position":16,"surface":"σιαγόνας","lemma":"σιαγόνας","strongs":"4600","morph":{"partOfSpeech":"Noun","casus":"Accusative","number":"Plural","gender":"Feminine","tense":null,"voice":null,"mood":null,"person":null},"id":"Ps.31.9.16","verseId":"Ps.31.9"},{"position":17,"surface":"αὐτῶν","lemma":"αὐτῶν","strongs":"846","morph":{"partOfSpeech":"Demonstrative","casus":"Genitive","number":"Plural","gender":"Masculine","tense":null,"voice":null,"mood":null,"person":null},"id":"Ps.31.9.17","verseId":"Ps.31.9"},{"position":18,"surface":"ἄγξαι","lemma":"ἄγξαι","strongs":"","morph":{"partOfSpeech":"Verb","casus":null,"number":null,"gender":null,"tense":"Aorist","voice":"Active","mood":"Infinitive","person":null},"id":"Ps.31.9.18","verseId":"Ps.31.9"},{"position":19,"surface":"τῶν","lemma":"τῶν","strongs":"3588","morph":{"partOfSpeech":"Article","casus":"Genitive","number":"Plural","gender":"Masculine","tense":null,"voice":null,"mood":null,"person":null},"id":"Ps.31.9.19","verseId":"Ps.31.9"},{"position":20,"surface":"μὴ","lemma":"μὴ","strongs":"3361","morph":{"partOfSpeech":"Adverb","casus":null,"number":null,"gender":null,"tense":null,"voice":null,"mood":null,"person":null},"id":"Ps.31.9.20","verseId":"Ps.31.9"},{"position":21,"surface":"ἐγγιζόντων","lemma":"ἐγγιζόντων","strongs":"1448","morph":{"partOfSpeech":"Verb","casus":"Genitive","number":"Plural","gender":"Masculine","tense":"Present","voice":"Active","mood":"Participle","person":null},"id":"Ps.31.9.21","verseId":"Ps.31.9"},{"position":22,"surface":"πρὸς","lemma":"πρὸς","strongs":"4314","morph":{"partOfSpeech":"Preposition","casus":null,"number":null,"gender":null,"tense":null,"voice":null,"mood":null,"person":null},"id":"Ps.31.9.22","verseId":"Ps.31.9"},{"position":23,"surface":"σέ","lemma":"σέ","strongs":"4571","morph":{"partOfSpeech":"RP","casus":"Accusative","number":"Singular","tense":null,"voice":null,"mood":null,"person":null},"id":"Ps.31.9.23","verseId":"Ps.31.9"}]},{"id":"Ps.31.10","bookId":"Ps","chapter":31,"verse":10,"reference":"Psalms 31:10","text":"πολλαὶ αἱ μάστιγες τοῦ ἁμαρτωλοῦ τὸν δὲ ἐλπίζοντα ἐπὶ κύριον ἔλεος κυκλώσει","words":[{"position":1,"surface":"πολλαὶ","lemma":"πολλαὶ","strongs":"4183","morph":{"partOfSpeech":"Adjective","casus":"Nominative","number":"Plural","gender":"Feminine","tense":null,"voice":null,"mood":null,"person":null},"id":"Ps.31.10.1","verseId":"Ps.31.10"},{"position":2,"surface":"αἱ","lemma":"αἱ","strongs":"3588","morph":{"partOfSpeech":"Article","casus":"Nominative","number":"Plural","gender":"Feminine","tense":null,"voice":null,"mood":null,"person":null},"id":"Ps.31.10.2","verseId":"Ps.31.10"},{"position":3,"surface":"μάστιγες","lemma":"μάστιγες","strongs":"3148","morph":{"partOfSpeech":"Noun","casus":"Nominative","number":"Plural","gender":"Feminine","tense":null,"voice":null,"mood":null,"person":null},"id":"Ps.31.10.3","verseId":"Ps.31.10"},{"position":4,"surface":"τοῦ","lemma":"τοῦ","strongs":"3588","morph":{"partOfSpeech":"Article","casus":"Genitive","number":"Singular","gender":"Masculine","tense":null,"voice":null,"mood":null,"person":null},"id":"Ps.31.10.4","verseId":"Ps.31.10"},{"position":5,"surface":"ἁμαρτωλοῦ","lemma":"ἁμαρτωλοῦ","strongs":"268","morph":{"partOfSpeech":"Adjective","casus":"Genitive","number":"Singular","gender":"Masculine","tense":null,"voice":null,"mood":null,"person":null},"id":"Ps.31.10.5","verseId":"Ps.31.10"},{"position":6,"surface":"τὸν","lemma":"τὸν","strongs":"3588","morph":{"partOfSpeech":"Article","casus":"Accusative","number":"Singular","gender":"Masculine","tense":null,"voice":null,"mood":null,"person":null},"id":"Ps.31.10.6","verseId":"Ps.31.10"},{"position":7,"surface":"δὲ","lemma":"δὲ","strongs":"1161","morph":{"partOfSpeech":"Particle","casus":null,"number":null,"gender":null,"tense":null,"voice":null,"mood":null,"person":null},"id":"Ps.31.10.7","verseId":"Ps.31.10"},{"position":8,"surface":"ἐλπίζοντα","lemma":"ἐλπίζοντα","strongs":"1679","morph":{"partOfSpeech":"Verb","casus":"Accusative","number":"Singular","gender":"Masculine","tense":"Present","voice":"Active","mood":"Participle","person":null},"id":"Ps.31.10.8","verseId":"Ps.31.10"},{"position":9,"surface":"ἐπὶ","lemma":"ἐπὶ","strongs":"1909","morph":{"partOfSpeech":"Preposition","casus":null,"number":null,"gender":null,"tense":null,"voice":null,"mood":null,"person":null},"id":"Ps.31.10.9","verseId":"Ps.31.10"},{"position":10,"surface":"κύριον","lemma":"κύριον","strongs":"2962","morph":{"partOfSpeech":"Noun","casus":"Accusative","number":"Singular","gender":"Masculine","tense":null,"voice":null,"mood":null,"person":null},"id":"Ps.31.10.10","verseId":"Ps.31.10"},{"position":11,"surface":"ἔλεος","lemma":"ἔλεος","strongs":"1656","morph":{"partOfSpeech":"Noun","casus":"Nominative","number":"Singular","gender":"Neuter","tense":null,"voice":null,"mood":null,"person":null},"id":"Ps.31.10.11","verseId":"Ps.31.10"},{"position":12,"surface":"κυκλώσει","lemma":"κυκλώσει","strongs":"2944","morph":{"partOfSpeech":"Verb","casus":null,"number":"Singular","gender":null,"tense":"Future","voice":"Active","mood":"Indicative","person":"3"},"id":"Ps.31.10.12","verseId":"Ps.31.10"}]},{"id":"Ps.31.11","bookId":"Ps","chapter":31,"verse":11,"reference":"Psalms 31:11","text":"εὐφράνθητε ἐπὶ κύριον καὶ ἀγαλλιᾶσθε δίκαιοι καὶ καυχᾶσθε πάντες οἱ εὐθεῖς τῇ καρδίᾳ","words":[{"position":1,"surface":"εὐφράνθητε","lemma":"εὐφράνθητε","strongs":"2165","morph":{"partOfSpeech":"Verb","casus":null,"number":"Plural","gender":null,"tense":"Aorist","voice":"Passive","mood":"Imperative","person":"2"},"id":"Ps.31.11.1","verseId":"Ps.31.11"},{"position":2,"surface":"ἐπὶ","lemma":"ἐπὶ","strongs":"1909","morph":{"partOfSpeech":"Preposition","casus":null,"number":null,"gender":null,"tense":null,"voice":null,"mood":null,"person":null},"id":"Ps.31.11.2","verseId":"Ps.31.11"},{"position":3,"surface":"κύριον","lemma":"κύριον","strongs":"2962","morph":{"partOfSpeech":"Noun","casus":"Accusative","number":"Singular","gender":"Masculine","tense":null,"voice":null,"mood":null,"person":null},"id":"Ps.31.11.3","verseId":"Ps.31.11"},{"position":4,"surface":"καὶ","lemma":"καὶ","strongs":"2532","morph":{"partOfSpeech":"Conjunction","casus":null,"number":null,"gender":null,"tense":null,"voice":null,"mood":null,"person":null},"id":"Ps.31.11.4","verseId":"Ps.31.11"},{"position":5,"surface":"ἀγαλλιᾶσθε","lemma":"ἀγαλλιᾶσθε","strongs":"21","morph":{"partOfSpeech":"Verb","casus":null,"number":"Plural","gender":null,"tense":"Present","voice":"Middle","mood":"Imperative","person":"2"},"id":"Ps.31.11.5","verseId":"Ps.31.11"},{"position":6,"surface":"δίκαιοι","lemma":"δίκαιοι","strongs":"1342","morph":{"partOfSpeech":"Adjective","casus":"Nominative","number":"Plural","gender":"Masculine","tense":null,"voice":null,"mood":null,"person":null},"id":"Ps.31.11.6","verseId":"Ps.31.11"},{"position":7,"surface":"καὶ","lemma":"καὶ","strongs":"2532","morph":{"partOfSpeech":"Conjunction","casus":null,"number":null,"gender":null,"tense":null,"voice":null,"mood":null,"person":null},"id":"Ps.31.11.7","verseId":"Ps.31.11"},{"position":8,"surface":"καυχᾶσθε","lemma":"καυχᾶσθε","strongs":"2744","morph":{"partOfSpeech":"Verb","casus":null,"number":"Plural","gender":null,"tense":"Present","voice":"Middle","mood":"Imperative","person":"2"},"id":"Ps.31.11.8","verseId":"Ps.31.11"},{"position":9,"surface":"πάντες","lemma":"πάντες","strongs":"3956","morph":{"partOfSpeech":"Adjective","casus":"Nominative","number":"Plural","gender":"Masculine","tense":null,"voice":null,"mood":null,"person":null},"id":"Ps.31.11.9","verseId":"Ps.31.11"},{"position":10,"surface":"οἱ","lemma":"οἱ","strongs":"3588","morph":{"partOfSpeech":"Article","casus":"Nominative","number":"Plural","gender":"Masculine","tense":null,"voice":null,"mood":null,"person":null},"id":"Ps.31.11.10","verseId":"Ps.31.11"},{"position":11,"surface":"εὐθεῖς","lemma":"εὐθεῖς","strongs":"2117","morph":{"partOfSpeech":"Adjective","casus":"Nominative","number":"Plural","gender":"Masculine","tense":null,"voice":null,"mood":null,"person":null},"id":"Ps.31.11.11","verseId":"Ps.31.11"},{"position":12,"surface":"τῇ","lemma":"τῇ","strongs":"3588","morph":{"partOfSpeech":"Article","casus":"Dative","number":"Singular","gender":"Feminine","tense":null,"voice":null,"mood":null,"person":null},"id":"Ps.31.11.12","verseId":"Ps.31.11"},{"position":13,"surface":"καρδίᾳ","lemma":"καρδίᾳ","strongs":"2588","morph":{"partOfSpeech":"Noun","casus":"Dative","number":"Singular","gender":"Feminine","tense":null,"voice":null,"mood":null,"person":null},"id":"Ps.31.11.13","verseId":"Ps.31.11"}]}]}